[
  {
    "idmiejscowosc": "0092315",
    "nazwa": "Bielawy"
  },
  {
    "idmiejscowosc": "0092456",
    "nazwa": "Bogacin"
  },
  {
    "idmiejscowosc": "0092321",
    "nazwa": "Chrząstowo"
  },
  {
    "idmiejscowosc": "0092500",
    "nazwa": "Elżbiecin"
  },
  {
    "idmiejscowosc": "0092551",
    "nazwa": "Gabrielin"
  },
  {
    "idmiejscowosc": "0092338",
    "nazwa": "Gorzeń"
  },
  {
    "idmiejscowosc": "1066857",
    "nazwa": "Gostusza"
  },
  {
    "idmiejscowosc": "0092380",
    "nazwa": "Gumnowice"
  },
  {
    "idmiejscowosc": "0092611",
    "nazwa": "Janowo"
  },
  {
    "idmiejscowosc": "0092396",
    "nazwa": "Karnowo"
  },
  {
    "idmiejscowosc": "0092410",
    "nazwa": "Karnówko"
  },
  {
    "idmiejscowosc": "0092568",
    "nazwa": "Kazin"
  },
  {
    "idmiejscowosc": "0092344",
    "nazwa": "Kaźmierowo"
  },
  {
    "idmiejscowosc": "0092427",
    "nazwa": "Lubaszcz"
  },
  {
    "idmiejscowosc": "0092433",
    "nazwa": "Małocin"
  },
  {
    "idmiejscowosc": "0092440",
    "nazwa": "Michalin"
  },
  {
    "idmiejscowosc": "0092574",
    "nazwa": "Minikowo"
  },
  {
    "idmiejscowosc": "0092350",
    "nazwa": "Niedola"
  },
  {
    "idmiejscowosc": "0092404",
    "nazwa": "Nowakówko"
  },
  {
    "idmiejscowosc": "0092462",
    "nazwa": "Olszewka"
  },
  {
    "idmiejscowosc": "0092479",
    "nazwa": "Paterek"
  },
  {
    "idmiejscowosc": "0092367",
    "nazwa": "Piętacz"
  },
  {
    "idmiejscowosc": "0092485",
    "nazwa": "Polichno"
  },
  {
    "idmiejscowosc": "0092491",
    "nazwa": "Potulice"
  },
  {
    "idmiejscowosc": "0092516",
    "nazwa": "Rozwarzyn"
  },
  {
    "idmiejscowosc": "0092522",
    "nazwa": "Suchary"
  },
  {
    "idmiejscowosc": "0092539",
    "nazwa": "Ślesin"
  },
  {
    "idmiejscowosc": "0092580",
    "nazwa": "Trzeciewnica"
  },
  {
    "idmiejscowosc": "0092373",
    "nazwa": "Urszulin"
  },
  {
    "idmiejscowosc": "0092628",
    "nazwa": "Wieszki"
  },
  {
    "idmiejscowosc": "0092597",
    "nazwa": "Wieszki"
  },
  {
    "idmiejscowosc": "0092634",
    "nazwa": "Występ"
  }
]