[
  {
    "idulica": "00138",
    "nazwa": "Agatowa",
    "rodzaj": "ul."
  },
  {
    "idulica": "00157",
    "nazwa": "Akacjowa",
    "rodzaj": "ul."
  },
  {
    "idulica": "00167",
    "nazwa": "Aksamitna",
    "rodzaj": "ul."
  },
  {
    "idulica": "00432",
    "nazwa": "Armii Krajowej",
    "rodzaj": "ul."
  },
  {
    "idulica": "00584",
    "nazwa": "Bagienna",
    "rodzaj": "ul."
  },
  {
    "idulica": "00605",
    "nazwa": "Bajeczna",
    "rodzaj": "ul."
  },
  {
    "idulica": "00802",
    "nazwa": "Bartników",
    "rodzaj": "ul."
  },
  {
    "idulica": "00925",
    "nazwa": "Bażantowa",
    "rodzaj": "ul."
  },
  {
    "idulica": "00956",
    "nazwa": "Bednarska",
    "rodzaj": "ul."
  },
  {
    "idulica": "01184",
    "nazwa": "Białostocka",
    "rodzaj": "ul."
  },
  {
    "idulica": "01189",
    "nazwa": "Białowieska",
    "rodzaj": "ul."
  },
  {
    "idulica": "01279",
    "nazwa": "Bielska",
    "rodzaj": "ul."
  },
  {
    "idulica": "01413",
    "nazwa": "Bliska",
    "rodzaj": "ul."
  },
  {
    "idulica": "01518",
    "nazwa": "Bociania",
    "rodzaj": "ul."
  },
  {
    "idulica": "01528",
    "nazwa": "Boczna",
    "rodzaj": "ul."
  },
  {
    "idulica": "01679",
    "nazwa": "Bohaterów Warszawy",
    "rodzaj": "ul."
  },
  {
    "idulica": "01681",
    "nazwa": "Bohaterów Westerplatte",
    "rodzaj": "ul."
  },
  {
    "idulica": "01920",
    "nazwa": "Botaniczna",
    "rodzaj": "ul."
  },
  {
    "idulica": "02209",
    "nazwa": "Brylantowa",
    "rodzaj": "ul."
  },
  {
    "idulica": "02276",
    "nazwa": "Brzozowa",
    "rodzaj": "ul."
  },
  {
    "idulica": "02462",
    "nazwa": "Bursztynowa",
    "rodzaj": "ul."
  },
  {
    "idulica": "02602",
    "nazwa": "Celna",
    "rodzaj": "ul."
  },
  {
    "idulica": "42208",
    "nazwa": "abp. gen. dyw. Mirona Chodakowskiego",
    "rodzaj": "rondo"
  },
  {
    "idulica": "02849",
    "nazwa": "Fryderyka Chopina",
    "rodzaj": "ul."
  },
  {
    "idulica": "02964",
    "nazwa": "Ciasna",
    "rodzaj": "ul."
  },
  {
    "idulica": "02974",
    "nazwa": "Cicha",
    "rodzaj": "ul."
  },
  {
    "idulica": "03048",
    "nazwa": "Ciesielska",
    "rodzaj": "ul."
  },
  {
    "idulica": "03098",
    "nazwa": "Cisowa",
    "rodzaj": "ul."
  },
  {
    "idulica": "03191",
    "nazwa": "Cyprysowa",
    "rodzaj": "ul."
  },
  {
    "idulica": "46766",
    "nazwa": "Św. Św. Cyryla i Metodego",
    "rodzaj": "rondo"
  },
  {
    "idulica": "03227",
    "nazwa": "Czajki",
    "rodzaj": "ul."
  },
  {
    "idulica": "03450",
    "nazwa": "Czeska",
    "rodzaj": "ul."
  },
  {
    "idulica": "03557",
    "nazwa": "Daleka",
    "rodzaj": "ul."
  },
  {
    "idulica": "03585",
    "nazwa": "Daniela",
    "rodzaj": "ul."
  },
  {
    "idulica": "03811",
    "nazwa": "Dębowa",
    "rodzaj": "ul."
  },
  {
    "idulica": "03826",
    "nazwa": "Diamentowa",
    "rodzaj": "ul."
  },
  {
    "idulica": "03839",
    "nazwa": "Długa",
    "rodzaj": "ul."
  },
  {
    "idulica": "04034",
    "nazwa": "Dolna",
    "rodzaj": "ul."
  },
  {
    "idulica": "47947",
    "nazwa": "Doc. Adama Dowgirda",
    "rodzaj": "ul."
  },
  {
    "idulica": "04339",
    "nazwa": "Stanisława Duboisa",
    "rodzaj": "ul."
  },
  {
    "idulica": "04434",
    "nazwa": "Dworcowa",
    "rodzaj": "ul."
  },
  {
    "idulica": "04581",
    "nazwa": "Działowa",
    "rodzaj": "ul."
  },
  {
    "idulica": "04628",
    "nazwa": "Dzielnicowa",
    "rodzaj": "ul."
  },
  {
    "idulica": "28192",
    "nazwa": "ks. Antoniego Dziewiatowskiego",
    "rodzaj": "ul."
  },
  {
    "idulica": "04772",
    "nazwa": "Elektryczna",
    "rodzaj": "ul."
  },
  {
    "idulica": "04863",
    "nazwa": "Fabryczna",
    "rodzaj": "ul."
  },
  {
    "idulica": "46177",
    "nazwa": "Fabryka Chemiczna",
    "rodzaj": "ul."
  },
  {
    "idulica": "39343",
    "nazwa": "Jana Filipczuka",
    "rodzaj": "ul."
  },
  {
    "idulica": "05265",
    "nazwa": "Gajowa",
    "rodzaj": "ul."
  },
  {
    "idulica": "05476",
    "nazwa": "Gęsia",
    "rodzaj": "ul."
  },
  {
    "idulica": "05761",
    "nazwa": "Gołębia",
    "rodzaj": "ul."
  },
  {
    "idulica": "05948",
    "nazwa": "Górna",
    "rodzaj": "ul."
  },
  {
    "idulica": "06029",
    "nazwa": "Grabowa",
    "rodzaj": "ul."
  },
  {
    "idulica": "06075",
    "nazwa": "Graniczna",
    "rodzaj": "ul."
  },
  {
    "idulica": "06077",
    "nazwa": "Granitowa",
    "rodzaj": "ul."
  },
  {
    "idulica": "06255",
    "nazwa": "Gruntowa",
    "rodzaj": "ul."
  },
  {
    "idulica": "06260",
    "nazwa": "Grunwaldzka",
    "rodzaj": "ul."
  },
  {
    "idulica": "06507",
    "nazwa": "Handlowa",
    "rodzaj": "ul."
  },
  {
    "idulica": "06860",
    "nazwa": "Iglasta",
    "rodzaj": "ul."
  },
  {
    "idulica": "07097",
    "nazwa": "Jałowcowa",
    "rodzaj": "ul."
  },
  {
    "idulica": "07290",
    "nazwa": "Jarzębinowa",
    "rodzaj": "ul."
  },
  {
    "idulica": "07329",
    "nazwa": "Jaskółcza",
    "rodzaj": "ul."
  },
  {
    "idulica": "07380",
    "nazwa": "Jaśminowa",
    "rodzaj": "ul."
  },
  {
    "idulica": "07354",
    "nazwa": "Jastrzębia",
    "rodzaj": "ul."
  },
  {
    "idulica": "07394",
    "nazwa": "Jaworowa",
    "rodzaj": "ul."
  },
  {
    "idulica": "07455",
    "nazwa": "Jelenia",
    "rodzaj": "ul."
  },
  {
    "idulica": "07506",
    "nazwa": "Jesionowa",
    "rodzaj": "ul."
  },
  {
    "idulica": "07582",
    "nazwa": "Jodłowa",
    "rodzaj": "ul."
  },
  {
    "idulica": "47076",
    "nazwa": "Judzianka Stara",
    "rodzaj": "ul."
  },
  {
    "idulica": "07699",
    "nazwa": "Jutrzenki",
    "rodzaj": "ul."
  },
  {
    "idulica": "07715",
    "nazwa": "Kacza",
    "rodzaj": "ul."
  },
  {
    "idulica": "07879",
    "nazwa": "Kamienna",
    "rodzaj": "ul."
  },
  {
    "idulica": "08171",
    "nazwa": "Kasztanowa",
    "rodzaj": "ul."
  },
  {
    "idulica": "39337",
    "nazwa": "Klimek",
    "rodzaj": "ul."
  },
  {
    "idulica": "08574",
    "nazwa": "Klonowa",
    "rodzaj": "ul."
  },
  {
    "idulica": "08633",
    "nazwa": "Kłosowa",
    "rodzaj": "ul."
  },
  {
    "idulica": "08728",
    "nazwa": "Jana Kochanowskiego",
    "rodzaj": "ul."
  },
  {
    "idulica": "08994",
    "nazwa": "Jakuba Kołasa",
    "rodzaj": "ul."
  },
  {
    "idulica": "08824",
    "nazwa": "Kolejki Leśne",
    "rodzaj": "ul."
  },
  {
    "idulica": "08828",
    "nazwa": "Kolejowa",
    "rodzaj": "ul."
  },
  {
    "idulica": "28081",
    "nazwa": "Hugo Kołłątaja",
    "rodzaj": "ul."
  },
  {
    "idulica": "42281",
    "nazwa": "Wincentego Kołodzieja",
    "rodzaj": "ul."
  },
  {
    "idulica": "38462",
    "nazwa": "Kolonia Poryjewo",
    "rodzaj": "ul."
  },
  {
    "idulica": "09018",
    "nazwa": "Kołowa",
    "rodzaj": "ul."
  },
  {
    "idulica": "09186",
    "nazwa": "Marii Konopnickiej",
    "rodzaj": "ul."
  },
  {
    "idulica": "09223",
    "nazwa": "Konwaliowa",
    "rodzaj": "ul."
  },
  {
    "idulica": "09582",
    "nazwa": "Tadeusza Kościuszki",
    "rodzaj": "ul."
  },
  {
    "idulica": "09424",
    "nazwa": "Kosidłów",
    "rodzaj": "ul."
  },
  {
    "idulica": "09819",
    "nazwa": "Krańcowa",
    "rodzaj": "ul."
  },
  {
    "idulica": "09871",
    "nazwa": "Józefa Ignacego Kraszewskiego",
    "rodzaj": "ul."
  },
  {
    "idulica": "10009",
    "nazwa": "Krótka",
    "rodzaj": "ul."
  },
  {
    "idulica": "10013",
    "nazwa": "Krucza",
    "rodzaj": "ul."
  },
  {
    "idulica": "10081",
    "nazwa": "Kryształowa",
    "rodzaj": "ul."
  },
  {
    "idulica": "10157",
    "nazwa": "Krzywa",
    "rodzaj": "ul."
  },
  {
    "idulica": "10268",
    "nazwa": "Księżycowa",
    "rodzaj": "ul."
  },
  {
    "idulica": "10361",
    "nazwa": "Kukułki",
    "rodzaj": "ul."
  },
  {
    "idulica": "10414",
    "nazwa": "Janki Kupały",
    "rodzaj": "ul."
  },
  {
    "idulica": "10562",
    "nazwa": "Kwiatowa",
    "rodzaj": "ul."
  },
  {
    "idulica": "11474",
    "nazwa": "Łabędzia",
    "rodzaj": "ul."
  },
  {
    "idulica": "11501",
    "nazwa": "Łagodna",
    "rodzaj": "ul."
  },
  {
    "idulica": "11596",
    "nazwa": "Łąkowa",
    "rodzaj": "ul."
  },
  {
    "idulica": "10718",
    "nazwa": "Lawendowa",
    "rodzaj": "ul."
  },
  {
    "idulica": "38956",
    "nazwa": "Stanisława Lema",
    "rodzaj": "ul."
  },
  {
    "idulica": "10898",
    "nazwa": "Leśna",
    "rodzaj": "ul."
  },
  {
    "idulica": "10870",
    "nazwa": "Leszczynowa",
    "rodzaj": "ul."
  },
  {
    "idulica": "10966",
    "nazwa": "Letnia",
    "rodzaj": "ul."
  },
  {
    "idulica": "11139",
    "nazwa": "Lipowa",
    "rodzaj": "ul."
  },
  {
    "idulica": "11205",
    "nazwa": "11 Listopada",
    "rodzaj": "ul."
  },
  {
    "idulica": "11671",
    "nazwa": "Łosia",
    "rodzaj": "ul."
  },
  {
    "idulica": "11690",
    "nazwa": "Łowcza",
    "rodzaj": "ul."
  },
  {
    "idulica": "11891",
    "nazwa": "Magazynowa",
    "rodzaj": "ul."
  },
  {
    "idulica": "11908",
    "nazwa": "Magnoliowa",
    "rodzaj": "ul."
  },
  {
    "idulica": "11937",
    "nazwa": "3 Maja",
    "rodzaj": "ul."
  },
  {
    "idulica": "12004",
    "nazwa": "Makowa",
    "rodzaj": "ul."
  },
  {
    "idulica": "12098",
    "nazwa": "Mała",
    "rodzaj": "ul."
  },
  {
    "idulica": "12065",
    "nazwa": "Malinowa",
    "rodzaj": "ul."
  },
  {
    "idulica": "12183",
    "nazwa": "Małomiejska",
    "rodzaj": "ul."
  },
  {
    "idulica": "12387",
    "nazwa": "Marmurowa",
    "rodzaj": "ul."
  },
  {
    "idulica": "12555",
    "nazwa": "Mazurska",
    "rodzaj": "ul."
  },
  {
    "idulica": "12559",
    "nazwa": "Mazury",
    "rodzaj": "ul."
  },
  {
    "idulica": "12627",
    "nazwa": "Metalowa",
    "rodzaj": "ul."
  },
  {
    "idulica": "12740",
    "nazwa": "Adama Mickiewicza",
    "rodzaj": "ul."
  },
  {
    "idulica": "12765",
    "nazwa": "Miedziana",
    "rodzaj": "ul."
  },
  {
    "idulica": "12863",
    "nazwa": "Międzytory",
    "rodzaj": "ul."
  },
  {
    "idulica": "12947",
    "nazwa": "Miła",
    "rodzaj": "ul."
  },
  {
    "idulica": "12954",
    "nazwa": "Stanisława Miłkowskiego",
    "rodzaj": "ul."
  },
  {
    "idulica": "12991",
    "nazwa": "Miodowa",
    "rodzaj": "ul."
  },
  {
    "idulica": "13184",
    "nazwa": "Modrzewiowa",
    "rodzaj": "ul."
  },
  {
    "idulica": "13246",
    "nazwa": "Stanisława Moniuszki",
    "rodzaj": "ul."
  },
  {
    "idulica": "13379",
    "nazwa": "Mostowa",
    "rodzaj": "ul."
  },
  {
    "idulica": "13563",
    "nazwa": "Myśliwska",
    "rodzaj": "ul."
  },
  {
    "idulica": "13861",
    "nazwa": "Nadbrzeżna",
    "rodzaj": "ul."
  },
  {
    "idulica": "13967",
    "nazwa": "Zofii Nałkowskiej",
    "rodzaj": "ul."
  },
  {
    "idulica": "14073",
    "nazwa": "Nektarowa",
    "rodzaj": "ul."
  },
  {
    "idulica": "14116",
    "nazwa": "Niecała",
    "rodzaj": "ul."
  },
  {
    "idulica": "14149",
    "nazwa": "Niedźwiedzia",
    "rodzaj": "ul."
  },
  {
    "idulica": "14330",
    "nazwa": "Nowa",
    "rodzaj": "ul."
  },
  {
    "idulica": "14492",
    "nazwa": "Nowowarszawska",
    "rodzaj": "ul."
  },
  {
    "idulica": "14685",
    "nazwa": "Obwodowa",
    "rodzaj": "ul."
  },
  {
    "idulica": "14687",
    "nazwa": "Oceaniczna",
    "rodzaj": "ul."
  },
  {
    "idulica": "14735",
    "nazwa": "Odległa",
    "rodzaj": "ul."
  },
  {
    "idulica": "26962",
    "nazwa": "Michała Ogińskiego",
    "rodzaj": "ul."
  },
  {
    "idulica": "14834",
    "nazwa": "Ogrodowa",
    "rodzaj": "ul."
  },
  {
    "idulica": "14886",
    "nazwa": "Okopowa",
    "rodzaj": "ul."
  },
  {
    "idulica": "15202",
    "nazwa": "Orzechowa",
    "rodzaj": "ul."
  },
  {
    "idulica": "15211",
    "nazwa": "Elizy Orzeszkowej",
    "rodzaj": "ul."
  },
  {
    "idulica": "47077",
    "nazwa": "Osiedle Millenium",
    "rodzaj": "ul."
  },
  {
    "idulica": "15479",
    "nazwa": "Owocowa",
    "rodzaj": "ul."
  },
  {
    "idulica": "15710",
    "nazwa": "Parkowa",
    "rodzaj": "ul."
  },
  {
    "idulica": "15729",
    "nazwa": "Partyzancka",
    "rodzaj": "ul."
  },
  {
    "idulica": "15832",
    "nazwa": "Pawia",
    "rodzaj": "ul."
  },
  {
    "idulica": "16027",
    "nazwa": "Piaski",
    "rodzaj": "ul."
  },
  {
    "idulica": "36029",
    "nazwa": "Marszałka Józefa Piłsudskiego",
    "rodzaj": "ul."
  },
  {
    "idulica": "16455",
    "nazwa": "Platynowa",
    "rodzaj": "ul."
  },
  {
    "idulica": "16721",
    "nazwa": "Poddolna",
    "rodzaj": "ul."
  },
  {
    "idulica": "16791",
    "nazwa": "Podlasie",
    "rodzaj": "ul."
  },
  {
    "idulica": "16816",
    "nazwa": "Podmiejska",
    "rodzaj": "ul."
  },
  {
    "idulica": "16900",
    "nazwa": "Pogodna",
    "rodzaj": "ul."
  },
  {
    "idulica": "17011",
    "nazwa": "Polna",
    "rodzaj": "ul."
  },
  {
    "idulica": "17070",
    "nazwa": "Południowa",
    "rodzaj": "ul."
  },
  {
    "idulica": "46816",
    "nazwa": "Pelagii Ponieckiej",
    "rodzaj": "ul."
  },
  {
    "idulica": "17171",
    "nazwa": "Poprzeczna",
    "rodzaj": "ul."
  },
  {
    "idulica": "17188",
    "nazwa": "Poranek",
    "rodzaj": "ul."
  },
  {
    "idulica": "17223",
    "nazwa": "Poryjewo",
    "rodzaj": "ul."
  },
  {
    "idulica": "17390",
    "nazwa": "Poziomkowa",
    "rodzaj": "ul."
  },
  {
    "idulica": "51123",
    "nazwa": "Propolisowa",
    "rodzaj": "ul."
  },
  {
    "idulica": "17547",
    "nazwa": "Prosta",
    "rodzaj": "ul."
  },
  {
    "idulica": "17577",
    "nazwa": "Bolesława Prusa",
    "rodzaj": "ul."
  },
  {
    "idulica": "18006",
    "nazwa": "Przytorowa",
    "rodzaj": "ul."
  },
  {
    "idulica": "18035",
    "nazwa": "Pszczela",
    "rodzaj": "ul."
  },
  {
    "idulica": "18048",
    "nazwa": "Pszeniczna",
    "rodzaj": "ul."
  },
  {
    "idulica": "42282",
    "nazwa": "dr. Kazimierza Ptaszyńskiego",
    "rodzaj": "ul."
  },
  {
    "idulica": "52857",
    "nazwa": "Pyłkowa",
    "rodzaj": "ul."
  },
  {
    "idulica": "36097",
    "nazwa": "dr. Tadeusza Rakowieckiego",
    "rodzaj": "ul."
  },
  {
    "idulica": "18565",
    "nazwa": "Mikołaja Reja",
    "rodzaj": "ul."
  },
  {
    "idulica": "46627",
    "nazwa": "Rondo Świętego Jana Pawła II",
    "rodzaj": "rondo"
  },
  {
    "idulica": "19000",
    "nazwa": "Różana",
    "rodzaj": "ul."
  },
  {
    "idulica": "19094",
    "nazwa": "Rumiankowa",
    "rodzaj": "ul."
  },
  {
    "idulica": "19295",
    "nazwa": "Rysia",
    "rodzaj": "ul."
  },
  {
    "idulica": "19326",
    "nazwa": "Rzeczna",
    "rodzaj": "ul."
  },
  {
    "idulica": "19404",
    "nazwa": "Sadowa",
    "rodzaj": "ul."
  },
  {
    "idulica": "19536",
    "nazwa": "Sarnia",
    "rodzaj": "ul."
  },
  {
    "idulica": "22290",
    "nazwa": "ks. Piotra Ściegiennego",
    "rodzaj": "ul."
  },
  {
    "idulica": "19834",
    "nazwa": "Henryka Sienkiewicza",
    "rodzaj": "ul."
  },
  {
    "idulica": "19891",
    "nazwa": "Siewna",
    "rodzaj": "ul."
  },
  {
    "idulica": "19897",
    "nazwa": "Sikorki",
    "rodzaj": "ul."
  },
  {
    "idulica": "20015",
    "nazwa": "Skarpowa",
    "rodzaj": "ul."
  },
  {
    "idulica": "20068",
    "nazwa": "Marii Skłodowskiej-Curie",
    "rodzaj": "ul."
  },
  {
    "idulica": "20107",
    "nazwa": "Skośna",
    "rodzaj": "ul."
  },
  {
    "idulica": "20121",
    "nazwa": "Skowronka",
    "rodzaj": "ul."
  },
  {
    "idulica": "43825",
    "nazwa": "Skwer im. Plutonowego Bolesława Bierwiaczonka",
    "rodzaj": "skwer"
  },
  {
    "idulica": "20222",
    "nazwa": "Słodka",
    "rodzaj": "ul."
  },
  {
    "idulica": "20235",
    "nazwa": "Słomiana",
    "rodzaj": "ul."
  },
  {
    "idulica": "20254",
    "nazwa": "Słoneczna",
    "rodzaj": "ul."
  },
  {
    "idulica": "20258",
    "nazwa": "Słonecznikowa",
    "rodzaj": "ul."
  },
  {
    "idulica": "20291",
    "nazwa": "Juliusza Słowackiego",
    "rodzaj": "ul."
  },
  {
    "idulica": "20298",
    "nazwa": "Słowicza",
    "rodzaj": "ul."
  },
  {
    "idulica": "22351",
    "nazwa": "Ślusarska",
    "rodzaj": "ul."
  },
  {
    "idulica": "20478",
    "nazwa": "Sokola",
    "rodzaj": "ul."
  },
  {
    "idulica": "39255",
    "nazwa": "Tamary Sołoniewicz",
    "rodzaj": "ul."
  },
  {
    "idulica": "20598",
    "nazwa": "Sosnowa",
    "rodzaj": "ul."
  },
  {
    "idulica": "20615",
    "nazwa": "Sowia",
    "rodzaj": "ul."
  },
  {
    "idulica": "20647",
    "nazwa": "Spadowa",
    "rodzaj": "ul."
  },
  {
    "idulica": "20664",
    "nazwa": "Spiralna",
    "rodzaj": "ul."
  },
  {
    "idulica": "20670",
    "nazwa": "Spiżowa",
    "rodzaj": "ul."
  },
  {
    "idulica": "20677",
    "nazwa": "Spokojna",
    "rodzaj": "ul."
  },
  {
    "idulica": "20683",
    "nazwa": "Sportowa",
    "rodzaj": "ul."
  },
  {
    "idulica": "20808",
    "nazwa": "Stalowa",
    "rodzaj": "ul."
  },
  {
    "idulica": "21071",
    "nazwa": "Stanisława Staszica",
    "rodzaj": "ul."
  },
  {
    "idulica": "00891",
    "nazwa": "Stefana Batorego",
    "rodzaj": "ul."
  },
  {
    "idulica": "21231",
    "nazwa": "Stolarska",
    "rodzaj": "ul."
  },
  {
    "idulica": "21246",
    "nazwa": "Storczykowa",
    "rodzaj": "ul."
  },
  {
    "idulica": "46749",
    "nazwa": "Strażników Puszczy Białowieskiej",
    "rodzaj": "rondo"
  },
  {
    "idulica": "21381",
    "nazwa": "Strzelecka",
    "rodzaj": "ul."
  },
  {
    "idulica": "21425",
    "nazwa": "Studzienna",
    "rodzaj": "ul."
  },
  {
    "idulica": "22508",
    "nazwa": "Świerkowa",
    "rodzaj": "ul."
  },
  {
    "idulica": "22003",
    "nazwa": "Szmaragdowa",
    "rodzaj": "ul."
  },
  {
    "idulica": "39344",
    "nazwa": "Szosa Kleszczelowska",
    "rodzaj": "ul."
  },
  {
    "idulica": "22238",
    "nazwa": "Karola Szymanowskiego",
    "rodzaj": "ul."
  },
  {
    "idulica": "22659",
    "nazwa": "Targowa",
    "rodzaj": "ul."
  },
  {
    "idulica": "22777",
    "nazwa": "Tęczowa",
    "rodzaj": "ul."
  },
  {
    "idulica": "22880",
    "nazwa": "Topolowa",
    "rodzaj": "ul."
  },
  {
    "idulica": "22897",
    "nazwa": "Torowa",
    "rodzaj": "ul."
  },
  {
    "idulica": "23033",
    "nazwa": "Truskawkowa",
    "rodzaj": "ul."
  },
  {
    "idulica": "23129",
    "nazwa": "Tulipanowa",
    "rodzaj": "ul."
  },
  {
    "idulica": "23196",
    "nazwa": "Juliana Tuwima",
    "rodzaj": "ul."
  },
  {
    "idulica": "23411",
    "nazwa": "Urodzajna",
    "rodzaj": "ul."
  },
  {
    "idulica": "23682",
    "nazwa": "Warszawska",
    "rodzaj": "ul."
  },
  {
    "idulica": "23713",
    "nazwa": "Warzywna",
    "rodzaj": "ul."
  },
  {
    "idulica": "23795",
    "nazwa": "Wąska",
    "rodzaj": "ul."
  },
  {
    "idulica": "23877",
    "nazwa": "Jana Werpachowskiego",
    "rodzaj": "ul."
  },
  {
    "idulica": "23884",
    "nazwa": "Wesoła",
    "rodzaj": "ul."
  },
  {
    "idulica": "23974",
    "nazwa": "Wiatrakowa",
    "rodzaj": "ul."
  },
  {
    "idulica": "24048",
    "nazwa": "Wiejska",
    "rodzaj": "ul."
  },
  {
    "idulica": "24123",
    "nazwa": "Henryka Wieniawskiego",
    "rodzaj": "ul."
  },
  {
    "idulica": "28193",
    "nazwa": "ks. Ignacego Wierobieja",
    "rodzaj": "ul."
  },
  {
    "idulica": "24208",
    "nazwa": "Wiewiórcza",
    "rodzaj": "ul."
  },
  {
    "idulica": "24261",
    "nazwa": "Wilcza",
    "rodzaj": "ul."
  },
  {
    "idulica": "24294",
    "nazwa": "Wilgi",
    "rodzaj": "ul."
  },
  {
    "idulica": "24364",
    "nazwa": "Wiosenna",
    "rodzaj": "ul."
  },
  {
    "idulica": "24494",
    "nazwa": "Władysława Jagiełły",
    "rodzaj": "ul."
  },
  {
    "idulica": "24628",
    "nazwa": "Wojska Polskiego",
    "rodzaj": "ul."
  },
  {
    "idulica": "24751",
    "nazwa": "Woskowa",
    "rodzaj": "ul."
  },
  {
    "idulica": "24838",
    "nazwa": "Walerego Wróblewskiego",
    "rodzaj": "ul."
  },
  {
    "idulica": "24870",
    "nazwa": "Wrzosowa",
    "rodzaj": "ul."
  },
  {
    "idulica": "42283",
    "nazwa": "Wydmuchowo",
    "rodzaj": "ul."
  },
  {
    "idulica": "26367",
    "nazwa": "Żabia",
    "rodzaj": "ul."
  },
  {
    "idulica": "39740",
    "nazwa": "Żabia Górka",
    "rodzaj": "ul."
  },
  {
    "idulica": "25427",
    "nazwa": "Zajęcza",
    "rodzaj": "ul."
  },
  {
    "idulica": "27428",
    "nazwa": "Zaułek Targowy",
    "rodzaj": "ul."
  },
  {
    "idulica": "25910",
    "nazwa": "Zbożowa",
    "rodzaj": "ul."
  },
  {
    "idulica": "26469",
    "nazwa": "Stefana Żeromskiego",
    "rodzaj": "ul."
  },
  {
    "idulica": "26081",
    "nazwa": "Zielona",
    "rodzaj": "ul."
  },
  {
    "idulica": "27965",
    "nazwa": "Aleksego Zina",
    "rodzaj": "ul."
  },
  {
    "idulica": "26188",
    "nazwa": "Złota",
    "rodzaj": "ul."
  },
  {
    "idulica": "26579",
    "nazwa": "Żurawia",
    "rodzaj": "ul."
  },
  {
    "idulica": "26305",
    "nazwa": "Zwierzyniecka",
    "rodzaj": "ul."
  },
  {
    "idulica": "26611",
    "nazwa": "Żwirowa",
    "rodzaj": "ul."
  },
  {
    "idulica": "26635",
    "nazwa": "Żytnia",
    "rodzaj": "ul."
  }
]