[
  {
    "idmiejscowosc": "0292936",
    "nazwa": "Baraniec"
  },
  {
    "idmiejscowosc": "0292942",
    "nazwa": "Benewicze"
  },
  {
    "idmiejscowosc": "0292853",
    "nazwa": "Białobrzeg"
  },
  {
    "idmiejscowosc": "0293195",
    "nazwa": "Białobrzeg Ratajski"
  },
  {
    "idmiejscowosc": "0292876",
    "nazwa": "Ciemierów"
  },
  {
    "idmiejscowosc": "0292882",
    "nazwa": "Ciemierów-Kolonia"
  },
  {
    "idmiejscowosc": "0292907",
    "nazwa": "Dłusk"
  },
  {
    "idmiejscowosc": "0292913",
    "nazwa": "Dolne Grądy"
  },
  {
    "idmiejscowosc": "0293203",
    "nazwa": "Glinianki"
  },
  {
    "idmiejscowosc": "0292988",
    "nazwa": "Górne Grądy"
  },
  {
    "idmiejscowosc": "0293002",
    "nazwa": "Kamień"
  },
  {
    "idmiejscowosc": "0292994",
    "nazwa": "Kolonia Janowska"
  },
  {
    "idmiejscowosc": "0292899",
    "nazwa": "Kolonia Lisewo"
  },
  {
    "idmiejscowosc": "0293137",
    "nazwa": "Królewiny"
  },
  {
    "idmiejscowosc": "0292959",
    "nazwa": "Kruszyny"
  },
  {
    "idmiejscowosc": "0293019",
    "nazwa": "Ksawerów"
  },
  {
    "idmiejscowosc": "0293025",
    "nazwa": "Lisewo"
  },
  {
    "idmiejscowosc": "0292965",
    "nazwa": "Lisiaki"
  },
  {
    "idmiejscowosc": "0293083",
    "nazwa": "Łupice"
  },
  {
    "idmiejscowosc": "0293090",
    "nazwa": "Modlica"
  },
  {
    "idmiejscowosc": "0293031",
    "nazwa": "Olsz"
  },
  {
    "idmiejscowosc": "0293048",
    "nazwa": "Pietrzyków"
  },
  {
    "idmiejscowosc": "0293054",
    "nazwa": "Pietrzyków-Kolonia"
  },
  {
    "idmiejscowosc": "0293060",
    "nazwa": "Rataje"
  },
  {
    "idmiejscowosc": "0293077",
    "nazwa": "Ruda Komorska"
  },
  {
    "idmiejscowosc": "0293114",
    "nazwa": "Tarnowa"
  },
  {
    "idmiejscowosc": "0293172",
    "nazwa": "Tarnowiec-Lasek"
  },
  {
    "idmiejscowosc": "0292971",
    "nazwa": "Tłoczyzna"
  },
  {
    "idmiejscowosc": "0293120",
    "nazwa": "Trzcianki"
  },
  {
    "idmiejscowosc": "0293143",
    "nazwa": "Walga"
  },
  {
    "idmiejscowosc": "0293150",
    "nazwa": "Wrąbczynek"
  },
  {
    "idmiejscowosc": "0293166",
    "nazwa": "Wrąbczynkowskie Holendry"
  },
  {
    "idmiejscowosc": "0293108",
    "nazwa": "Zamość"
  },
  {
    "idmiejscowosc": "0293189",
    "nazwa": "Zapowiednia"
  },
  {
    "idmiejscowosc": "0292920",
    "nazwa": "Zimochowiec"
  },
  {
    "idmiejscowosc": "0293210",
    "nazwa": "Żdżary"
  }
]