[
  {
    "idulica": "00729",
    "nazwa": "św. Barbary",
    "rodzaj": "ul."
  },
  {
    "idulica": "02148",
    "nazwa": "Browarna",
    "rodzaj": "ul."
  },
  {
    "idulica": "09546",
    "nazwa": "Kościelna",
    "rodzaj": "ul."
  },
  {
    "idulica": "09732",
    "nazwa": "Kozłowa",
    "rodzaj": "ul."
  },
  {
    "idulica": "10157",
    "nazwa": "Krzywa",
    "rodzaj": "ul."
  },
  {
    "idulica": "10898",
    "nazwa": "Leśna",
    "rodzaj": "ul."
  },
  {
    "idulica": "11891",
    "nazwa": "Magazynowa",
    "rodzaj": "ul."
  },
  {
    "idulica": "11937",
    "nazwa": "3 Maja",
    "rodzaj": "ul."
  },
  {
    "idulica": "12098",
    "nazwa": "Mała",
    "rodzaj": "ul."
  },
  {
    "idulica": "12842",
    "nazwa": "Mietlicka",
    "rodzaj": "ul."
  },
  {
    "idulica": "14330",
    "nazwa": "Nowa",
    "rodzaj": "ul."
  },
  {
    "idulica": "14535",
    "nazwa": "Nowy Świat",
    "rodzaj": "ul."
  },
  {
    "idulica": "14552",
    "nazwa": "Nurzecka",
    "rodzaj": "ul."
  },
  {
    "idulica": "15710",
    "nazwa": "Parkowa",
    "rodzaj": "ul."
  },
  {
    "idulica": "17011",
    "nazwa": "Polna",
    "rodzaj": "ul."
  },
  {
    "idulica": "19404",
    "nazwa": "Sadowa",
    "rodzaj": "ul."
  },
  {
    "idulica": "20054",
    "nazwa": "Sklepowa",
    "rodzaj": "ul."
  },
  {
    "idulica": "21970",
    "nazwa": "Szkolna",
    "rodzaj": "ul."
  },
  {
    "idulica": "24557",
    "nazwa": "Wodociągowa",
    "rodzaj": "ul."
  },
  {
    "idulica": "25266",
    "nazwa": "Zabłocka",
    "rodzaj": "ul."
  },
  {
    "idulica": "25400",
    "nazwa": "Zagumienna",
    "rodzaj": "ul."
  }
]