[
  {
    "idtech": "012",
    "idgmina": "01",
    "nazwa": "Aleksandrów",
    "kodrodzajgminy": "2",
    "rodzajgminy": "gmina wiejska"
  },
  {
    "idtech": "022",
    "idgmina": "02",
    "nazwa": "Czarnocin",
    "kodrodzajgminy": "2",
    "rodzajgminy": "gmina wiejska"
  },
  {
    "idtech": "032",
    "idgmina": "03",
    "nazwa": "Gorzkowice",
    "kodrodzajgminy": "2",
    "rodzajgminy": "gmina wiejska"
  },
  {
    "idtech": "042",
    "idgmina": "04",
    "nazwa": "Grabica",
    "kodrodzajgminy": "2",
    "rodzajgminy": "gmina wiejska"
  },
  {
    "idtech": "052",
    "idgmina": "05",
    "nazwa": "Łęki Szlacheckie",
    "kodrodzajgminy": "2",
    "rodzajgminy": "gmina wiejska"
  },
  {
    "idtech": "062",
    "idgmina": "06",
    "nazwa": "Moszczenica",
    "kodrodzajgminy": "2",
    "rodzajgminy": "gmina wiejska"
  },
  {
    "idtech": "072",
    "idgmina": "07",
    "nazwa": "Ręczno",
    "kodrodzajgminy": "2",
    "rodzajgminy": "gmina wiejska"
  },
  {
    "idtech": "084",
    "idgmina": "08",
    "nazwa": "Rozprza",
    "kodrodzajgminy": "4",
    "rodzajgminy": "miasto"
  },
  {
    "idtech": "085",
    "idgmina": "08",
    "nazwa": "Rozprza",
    "kodrodzajgminy": "5",
    "rodzajgminy": "obszar wiejski"
  },
  {
    "idtech": "094",
    "idgmina": "09",
    "nazwa": "Sulejów",
    "kodrodzajgminy": "4",
    "rodzajgminy": "miasto"
  },
  {
    "idtech": "095",
    "idgmina": "09",
    "nazwa": "Sulejów",
    "kodrodzajgminy": "5",
    "rodzajgminy": "obszar wiejski"
  },
  {
    "idtech": "102",
    "idgmina": "10",
    "nazwa": "Wola Krzysztoporska",
    "kodrodzajgminy": "2",
    "rodzajgminy": "gmina wiejska"
  },
  {
    "idtech": "114",
    "idgmina": "11",
    "nazwa": "Wolbórz",
    "kodrodzajgminy": "4",
    "rodzajgminy": "miasto"
  },
  {
    "idtech": "115",
    "idgmina": "11",
    "nazwa": "Wolbórz",
    "kodrodzajgminy": "5",
    "rodzajgminy": "obszar wiejski"
  }
]