[
  {
    "idmiejscowosc": "0814487",
    "nazwa": "Bączałka"
  },
  {
    "idmiejscowosc": "0814530",
    "nazwa": "Budy"
  },
  {
    "idmiejscowosc": "0814760",
    "nazwa": "Budy"
  },
  {
    "idmiejscowosc": "0814978",
    "nazwa": "Budy"
  },
  {
    "idmiejscowosc": "0814524",
    "nazwa": "Bukowa"
  },
  {
    "idmiejscowosc": "0814984",
    "nazwa": "Czapiec"
  },
  {
    "idmiejscowosc": "0815050",
    "nazwa": "Dąbie"
  },
  {
    "idmiejscowosc": "1042288",
    "nazwa": "Dąbrówka"
  },
  {
    "idmiejscowosc": "0814694",
    "nazwa": "Działy"
  },
  {
    "idmiejscowosc": "0814642",
    "nazwa": "Gąsiorówki"
  },
  {
    "idmiejscowosc": "0814576",
    "nazwa": "Głobikówka"
  },
  {
    "idmiejscowosc": "0814582",
    "nazwa": "Gorzejowa"
  },
  {
    "idmiejscowosc": "0814547",
    "nazwa": "Góry"
  },
  {
    "idmiejscowosc": "0815073",
    "nazwa": "Góry"
  },
  {
    "idmiejscowosc": "0814599",
    "nazwa": "Góry Południowe"
  },
  {
    "idmiejscowosc": "0814607",
    "nazwa": "Góry Północne"
  },
  {
    "idmiejscowosc": "0814659",
    "nazwa": "Granice"
  },
  {
    "idmiejscowosc": "0814777",
    "nazwa": "Granice"
  },
  {
    "idmiejscowosc": "0814613",
    "nazwa": "Grudna Dolna"
  },
  {
    "idmiejscowosc": "0814636",
    "nazwa": "Grudna Górna"
  },
  {
    "idmiejscowosc": "0814926",
    "nazwa": "Huta"
  },
  {
    "idmiejscowosc": "0814688",
    "nazwa": "Januszkowice"
  },
  {
    "idmiejscowosc": "0814731",
    "nazwa": "Kamienica Dolna"
  },
  {
    "idmiejscowosc": "0814754",
    "nazwa": "Kamienica Górna"
  },
  {
    "idmiejscowosc": "0814932",
    "nazwa": "Kamionki"
  },
  {
    "idmiejscowosc": "0814783",
    "nazwa": "Klecie"
  },
  {
    "idmiejscowosc": "0814949",
    "nazwa": "Kmiecie"
  },
  {
    "idmiejscowosc": "0814955",
    "nazwa": "Kopaliny"
  },
  {
    "idmiejscowosc": "0815021",
    "nazwa": "Kopaliny"
  },
  {
    "idmiejscowosc": "0814620",
    "nazwa": "Kopalnia"
  },
  {
    "idmiejscowosc": "0814665",
    "nazwa": "Kujawy"
  },
  {
    "idmiejscowosc": "0814889",
    "nazwa": "Laskowiec"
  },
  {
    "idmiejscowosc": "0814702",
    "nazwa": "Markosie"
  },
  {
    "idmiejscowosc": "0814837",
    "nazwa": "Nawsie Brzosteckie"
  },
  {
    "idmiejscowosc": "0814990",
    "nazwa": "Odwodzie"
  },
  {
    "idmiejscowosc": "1042294",
    "nazwa": "Okrągła"
  },
  {
    "idmiejscowosc": "0814866",
    "nazwa": "Opacionka"
  },
  {
    "idmiejscowosc": "0814719",
    "nazwa": "Piaski"
  },
  {
    "idmiejscowosc": "0814671",
    "nazwa": "Podkonie"
  },
  {
    "idmiejscowosc": "0814895",
    "nazwa": "Podlesie"
  },
  {
    "idmiejscowosc": "0815038",
    "nazwa": "Podlesie"
  },
  {
    "idmiejscowosc": "0814790",
    "nazwa": "Poręby"
  },
  {
    "idmiejscowosc": "0814808",
    "nazwa": "Postronie"
  },
  {
    "idmiejscowosc": "0814903",
    "nazwa": "Półanki"
  },
  {
    "idmiejscowosc": "0814872",
    "nazwa": "Przeczyca"
  },
  {
    "idmiejscowosc": "0814553",
    "nazwa": "Rzeki"
  },
  {
    "idmiejscowosc": "0815009",
    "nazwa": "Rzeki"
  },
  {
    "idmiejscowosc": "0814910",
    "nazwa": "Siedliska-Bogusz"
  },
  {
    "idmiejscowosc": "0814961",
    "nazwa": "Skurowa"
  },
  {
    "idmiejscowosc": "0815015",
    "nazwa": "Smarżowa"
  },
  {
    "idmiejscowosc": "0814814",
    "nazwa": "Stawiska"
  },
  {
    "idmiejscowosc": "0814748",
    "nazwa": "Wola"
  },
  {
    "idmiejscowosc": "0815044",
    "nazwa": "Wola Brzostecka"
  },
  {
    "idmiejscowosc": "0814725",
    "nazwa": "Zagórze"
  },
  {
    "idmiejscowosc": "0815067",
    "nazwa": "Zawadka Brzostecka"
  },
  {
    "idmiejscowosc": "0814820",
    "nazwa": "Zawodzie"
  },
  {
    "idmiejscowosc": "0814560",
    "nazwa": "Zawodzie"
  }
]