[
  {
    "idpowiat": "01",
    "nazwa": "bytowski",
    "nazwadod": "powiat"
  },
  {
    "idpowiat": "02",
    "nazwa": "chojnicki",
    "nazwadod": "powiat"
  },
  {
    "idpowiat": "03",
    "nazwa": "człuchowski",
    "nazwadod": "powiat"
  },
  {
    "idpowiat": "04",
    "nazwa": "gdański",
    "nazwadod": "powiat"
  },
  {
    "idpowiat": "05",
    "nazwa": "kartuski",
    "nazwadod": "powiat"
  },
  {
    "idpowiat": "06",
    "nazwa": "kościerski",
    "nazwadod": "powiat"
  },
  {
    "idpowiat": "07",
    "nazwa": "kwidzyński",
    "nazwadod": "powiat"
  },
  {
    "idpowiat": "08",
    "nazwa": "lęborski",
    "nazwadod": "powiat"
  },
  {
    "idpowiat": "09",
    "nazwa": "malborski",
    "nazwadod": "powiat"
  },
  {
    "idpowiat": "10",
    "nazwa": "nowodworski",
    "nazwadod": "powiat"
  },
  {
    "idpowiat": "11",
    "nazwa": "pucki",
    "nazwadod": "powiat"
  },
  {
    "idpowiat": "12",
    "nazwa": "słupski",
    "nazwadod": "powiat"
  },
  {
    "idpowiat": "13",
    "nazwa": "starogardzki",
    "nazwadod": "powiat"
  },
  {
    "idpowiat": "16",
    "nazwa": "sztumski",
    "nazwadod": "powiat"
  },
  {
    "idpowiat": "14",
    "nazwa": "tczewski",
    "nazwadod": "powiat"
  },
  {
    "idpowiat": "15",
    "nazwa": "wejherowski",
    "nazwadod": "powiat"
  },
  {
    "idpowiat": "61",
    "nazwa": "Gdańsk",
    "nazwadod": "miasto na prawach powiatu"
  },
  {
    "idpowiat": "62",
    "nazwa": "Gdynia",
    "nazwadod": "miasto na prawach powiatu"
  },
  {
    "idpowiat": "63",
    "nazwa": "Słupsk",
    "nazwadod": "miasto na prawach powiatu"
  },
  {
    "idpowiat": "64",
    "nazwa": "Sopot",
    "nazwadod": "miasto na prawach powiatu"
  }
]
