[
  {
    "idmiejscowosc": "0235660",
    "nazwa": "Będziaki"
  },
  {
    "idmiejscowosc": "0235677",
    "nazwa": "Bieglów"
  },
  {
    "idmiejscowosc": "0236122",
    "nazwa": "Bogoryja"
  },
  {
    "idmiejscowosc": "0235921",
    "nazwa": "Budziszowice"
  },
  {
    "idmiejscowosc": "0235683",
    "nazwa": "Bugaj"
  },
  {
    "idmiejscowosc": "0236270",
    "nazwa": "Bugaj Zagajowski"
  },
  {
    "idmiejscowosc": "0236151",
    "nazwa": "Chałupki"
  },
  {
    "idmiejscowosc": "0235973",
    "nazwa": "Chałupki Mękarzowskie"
  },
  {
    "idmiejscowosc": "0235714",
    "nazwa": "Charzowice"
  },
  {
    "idmiejscowosc": "0235737",
    "nazwa": "Cieszkowy"
  },
  {
    "idmiejscowosc": "0235789",
    "nazwa": "Ciuślice"
  },
  {
    "idmiejscowosc": "0235795",
    "nazwa": "Czarnocin"
  },
  {
    "idmiejscowosc": "0235832",
    "nazwa": "Dębiany"
  },
  {
    "idmiejscowosc": "0235720",
    "nazwa": "Dwór"
  },
  {
    "idmiejscowosc": "0235938",
    "nazwa": "Folwark"
  },
  {
    "idmiejscowosc": "0235803",
    "nazwa": "Gościniec"
  },
  {
    "idmiejscowosc": "0236079",
    "nazwa": "Gościniec"
  },
  {
    "idmiejscowosc": "0236033",
    "nazwa": "Gościniec"
  },
  {
    "idmiejscowosc": "0236091",
    "nazwa": "Gościniec"
  },
  {
    "idmiejscowosc": "0235944",
    "nazwa": "Góry Budziszowskie"
  },
  {
    "idmiejscowosc": "0235743",
    "nazwa": "Grabówka"
  },
  {
    "idmiejscowosc": "0236286",
    "nazwa": "Grabówka"
  },
  {
    "idmiejscowosc": "0236040",
    "nazwa": "Hektary"
  },
  {
    "idmiejscowosc": "0235750",
    "nazwa": "Jadwisin"
  },
  {
    "idmiejscowosc": "0236010",
    "nazwa": "Jadzinek"
  },
  {
    "idmiejscowosc": "0235810",
    "nazwa": "Kolonia"
  },
  {
    "idmiejscowosc": "0236139",
    "nazwa": "Kolonia"
  },
  {
    "idmiejscowosc": "0236197",
    "nazwa": "Kolonia"
  },
  {
    "idmiejscowosc": "0235861",
    "nazwa": "Kolosy"
  },
  {
    "idmiejscowosc": "0236168",
    "nazwa": "Kopanina"
  },
  {
    "idmiejscowosc": "0236205",
    "nazwa": "Korea"
  },
  {
    "idmiejscowosc": "0236240",
    "nazwa": "Korea"
  },
  {
    "idmiejscowosc": "0235884",
    "nazwa": "Koryto"
  },
  {
    "idmiejscowosc": "0235878",
    "nazwa": "Kosówka"
  },
  {
    "idmiejscowosc": "0235909",
    "nazwa": "Krzyż"
  },
  {
    "idmiejscowosc": "0235915",
    "nazwa": "Malżyce"
  },
  {
    "idmiejscowosc": "0235967",
    "nazwa": "Mękarzowice"
  },
  {
    "idmiejscowosc": "0235980",
    "nazwa": "Michałowice"
  },
  {
    "idmiejscowosc": "0236004",
    "nazwa": "Mikołajów"
  },
  {
    "idmiejscowosc": "0236027",
    "nazwa": "Miławczyce"
  },
  {
    "idmiejscowosc": "0235690",
    "nazwa": "Nowy Bieglów"
  },
  {
    "idmiejscowosc": "0235772",
    "nazwa": "Ogrody"
  },
  {
    "idmiejscowosc": "0236062",
    "nazwa": "Opatkowiczki"
  },
  {
    "idmiejscowosc": "0235890",
    "nazwa": "Parcelacja"
  },
  {
    "idmiejscowosc": "0235996",
    "nazwa": "Piekło"
  },
  {
    "idmiejscowosc": "0235855",
    "nazwa": "Podgaje"
  },
  {
    "idmiejscowosc": "0236292",
    "nazwa": "Podlesie"
  },
  {
    "idmiejscowosc": "0235950",
    "nazwa": "Sadzawka"
  },
  {
    "idmiejscowosc": "0236085",
    "nazwa": "Soboszów"
  },
  {
    "idmiejscowosc": "0236116",
    "nazwa": "Sokolina"
  },
  {
    "idmiejscowosc": "0235708",
    "nazwa": "Stary Bieglów"
  },
  {
    "idmiejscowosc": "0236145",
    "nazwa": "Stradów"
  },
  {
    "idmiejscowosc": "0236180",
    "nazwa": "Stropieszyn"
  },
  {
    "idmiejscowosc": "0236211",
    "nazwa": "Swoszowice"
  },
  {
    "idmiejscowosc": "0236234",
    "nazwa": "Turnawiec"
  },
  {
    "idmiejscowosc": "0236174",
    "nazwa": "Wierzbica"
  },
  {
    "idmiejscowosc": "0236257",
    "nazwa": "Zagaje Stradowskie"
  },
  {
    "idmiejscowosc": "0236263",
    "nazwa": "Zagajów"
  },
  {
    "idmiejscowosc": "0235826",
    "nazwa": "Zagrody"
  },
  {
    "idmiejscowosc": "0236100",
    "nazwa": "Zawada"
  },
  {
    "idmiejscowosc": "0236300",
    "nazwa": "Zielonki"
  },
  {
    "idmiejscowosc": "0236056",
    "nazwa": "Żabiniec"
  }
]