[
  {
    "idulica": "29286",
    "nazwa": "50-lecia Kopalni Konin",
    "rodzaj": "ul."
  },
  {
    "idulica": "00157",
    "nazwa": "Akacjowa",
    "rodzaj": "ul."
  },
  {
    "idulica": "54985",
    "nazwa": "aleja 600-lecia",
    "rodzaj": "ul."
  },
  {
    "idulica": "40651",
    "nazwa": "Świętej Barbary",
    "rodzaj": "ul."
  },
  {
    "idulica": "01172",
    "nazwa": "Białobrodzka",
    "rodzaj": "ul."
  },
  {
    "idulica": "01528",
    "nazwa": "Boczna",
    "rodzaj": "ul."
  },
  {
    "idulica": "01874",
    "nazwa": "Borówkowa",
    "rodzaj": "ul."
  },
  {
    "idulica": "02559",
    "nazwa": "Cechowa",
    "rodzaj": "ul."
  },
  {
    "idulica": "02844",
    "nazwa": "Chopina",
    "rodzaj": "ul."
  },
  {
    "idulica": "03811",
    "nazwa": "Dębowa",
    "rodzaj": "ul."
  },
  {
    "idulica": "04151",
    "nazwa": "Dożynkowa",
    "rodzaj": "ul."
  },
  {
    "idulica": "05027",
    "nazwa": "Fiołkowa",
    "rodzaj": "ul."
  },
  {
    "idulica": "05610",
    "nazwa": "Głogowa",
    "rodzaj": "ul."
  },
  {
    "idulica": "05962",
    "nazwa": "Górnicza",
    "rodzaj": "ul."
  },
  {
    "idulica": "06650",
    "nazwa": "Hiacyntowa",
    "rodzaj": "ul."
  },
  {
    "idulica": "06933",
    "nazwa": "Irysowa",
    "rodzaj": "ul."
  },
  {
    "idulica": "07059",
    "nazwa": "Jagodowa",
    "rodzaj": "ul."
  },
  {
    "idulica": "07123",
    "nazwa": "Jana Pawła II",
    "rodzaj": "ul."
  },
  {
    "idulica": "07380",
    "nazwa": "Jaśminowa",
    "rodzaj": "ul."
  },
  {
    "idulica": "07641",
    "nazwa": "Jubileuszowa",
    "rodzaj": "ul."
  },
  {
    "idulica": "07906",
    "nazwa": "gen. Franciszka Kamińskiego",
    "rodzaj": "ul."
  },
  {
    "idulica": "08171",
    "nazwa": "Kasztanowa",
    "rodzaj": "ul."
  },
  {
    "idulica": "41362",
    "nazwa": "Świętej Kingi",
    "rodzaj": "ul."
  },
  {
    "idulica": "08828",
    "nazwa": "Kolejowa",
    "rodzaj": "ul."
  },
  {
    "idulica": "09163",
    "nazwa": "Konińska",
    "rodzaj": "ul."
  },
  {
    "idulica": "09223",
    "nazwa": "Konwaliowa",
    "rodzaj": "ul."
  },
  {
    "idulica": "09546",
    "nazwa": "Kościelna",
    "rodzaj": "ul."
  },
  {
    "idulica": "09819",
    "nazwa": "Krańcowa",
    "rodzaj": "ul."
  },
  {
    "idulica": "09946",
    "nazwa": "Krokusowa",
    "rodzaj": "ul."
  },
  {
    "idulica": "10009",
    "nazwa": "Krótka",
    "rodzaj": "ul."
  },
  {
    "idulica": "11596",
    "nazwa": "Łąkowa",
    "rodzaj": "ul."
  },
  {
    "idulica": "10718",
    "nazwa": "Lawendowa",
    "rodzaj": "ul."
  },
  {
    "idulica": "10898",
    "nazwa": "Leśna",
    "rodzaj": "ul."
  },
  {
    "idulica": "11067",
    "nazwa": "Liliowa",
    "rodzaj": "ul."
  },
  {
    "idulica": "11205",
    "nazwa": "11 Listopada",
    "rodzaj": "ul."
  },
  {
    "idulica": "11937",
    "nazwa": "3 Maja",
    "rodzaj": "ul."
  },
  {
    "idulica": "12004",
    "nazwa": "Makowa",
    "rodzaj": "ul."
  },
  {
    "idulica": "12065",
    "nazwa": "Malinowa",
    "rodzaj": "ul."
  },
  {
    "idulica": "13112",
    "nazwa": "Młynarska",
    "rodzaj": "ul."
  },
  {
    "idulica": "39417",
    "nazwa": "Na Wzgórze",
    "rodzaj": "ul."
  },
  {
    "idulica": "14330",
    "nazwa": "Nowa",
    "rodzaj": "ul."
  },
  {
    "idulica": "14834",
    "nazwa": "Ogrodowa",
    "rodzaj": "ul."
  },
  {
    "idulica": "14909",
    "nazwa": "Okrzei",
    "rodzaj": "ul."
  },
  {
    "idulica": "16027",
    "nazwa": "Piaski",
    "rodzaj": "ul."
  },
  {
    "idulica": "59041",
    "nazwa": "pl. Józefa Piłsudskiego",
    "rodzaj": "ul."
  },
  {
    "idulica": "59040",
    "nazwa": "pl. Kościuszki",
    "rodzaj": "ul."
  },
  {
    "idulica": "59042",
    "nazwa": "pl. Wolności",
    "rodzaj": "ul."
  },
  {
    "idulica": "17011",
    "nazwa": "Polna",
    "rodzaj": "ul."
  },
  {
    "idulica": "17421",
    "nazwa": "Północna",
    "rodzaj": "ul."
  },
  {
    "idulica": "17149",
    "nazwa": "ks. Jerzego Popiełuszki",
    "rodzaj": "ul."
  },
  {
    "idulica": "17390",
    "nazwa": "Poziomkowa",
    "rodzaj": "ul."
  },
  {
    "idulica": "17394",
    "nazwa": "Poznańska",
    "rodzaj": "ul."
  },
  {
    "idulica": "17952",
    "nazwa": "Przylesie",
    "rodzaj": "ul."
  },
  {
    "idulica": "18217",
    "nazwa": "Alojzego Putza",
    "rodzaj": "ul."
  },
  {
    "idulica": "39827",
    "nazwa": "Rondo Miast Partnerskich",
    "rodzaj": "rondo"
  },
  {
    "idulica": "45411",
    "nazwa": "Rondo Powstańców Styczniowych",
    "rodzaj": "rondo"
  },
  {
    "idulica": "19000",
    "nazwa": "Różana",
    "rodzaj": "ul."
  },
  {
    "idulica": "19131",
    "nazwa": "Rutki",
    "rodzaj": "ul."
  },
  {
    "idulica": "19335",
    "nazwa": "Rzemieślnicza",
    "rodzaj": "ul."
  },
  {
    "idulica": "19549",
    "nazwa": "Sasankowa",
    "rodzaj": "ul."
  },
  {
    "idulica": "20254",
    "nazwa": "Słoneczna",
    "rodzaj": "ul."
  },
  {
    "idulica": "20532",
    "nazwa": "Solidarności",
    "rodzaj": "ul."
  },
  {
    "idulica": "20598",
    "nazwa": "Sosnowa",
    "rodzaj": "ul."
  },
  {
    "idulica": "20641",
    "nazwa": "Spacerowa",
    "rodzaj": "ul."
  },
  {
    "idulica": "21193",
    "nazwa": "Stodolna",
    "rodzaj": "ul."
  },
  {
    "idulica": "21228",
    "nazwa": "Stokrotkowa",
    "rodzaj": "ul."
  },
  {
    "idulica": "21271",
    "nazwa": "Strażacka",
    "rodzaj": "ul."
  },
  {
    "idulica": "21970",
    "nazwa": "Szkolna",
    "rodzaj": "ul."
  },
  {
    "idulica": "22659",
    "nazwa": "Targowa",
    "rodzaj": "ul."
  },
  {
    "idulica": "22902",
    "nazwa": "Toruńska",
    "rodzaj": "ul."
  },
  {
    "idulica": "23129",
    "nazwa": "Tulipanowa",
    "rodzaj": "ul."
  },
  {
    "idulica": "23682",
    "nazwa": "Warszawska",
    "rodzaj": "ul."
  },
  {
    "idulica": "23972",
    "nazwa": "Wiatraczna",
    "rodzaj": "ul."
  },
  {
    "idulica": "24477",
    "nazwa": "Wjazdowa",
    "rodzaj": "ul."
  },
  {
    "idulica": "24550",
    "nazwa": "Wodna",
    "rodzaj": "ul."
  },
  {
    "idulica": "25314",
    "nazwa": "Zacisze",
    "rodzaj": "ul."
  },
  {
    "idulica": "25438",
    "nazwa": "Zakątek",
    "rodzaj": "ul."
  },
  {
    "idulica": "26464",
    "nazwa": "Żeromskiego",
    "rodzaj": "ul."
  }
]