[
  {
    "idulica": "36834",
    "nazwa": "Aleja Dębowa",
    "rodzaj": "ul."
  },
  {
    "idulica": "01528",
    "nazwa": "Boczna",
    "rodzaj": "ul."
  },
  {
    "idulica": "04317",
    "nazwa": "Michała Drzymały",
    "rodzaj": "ul."
  },
  {
    "idulica": "10562",
    "nazwa": "Kwiatowa",
    "rodzaj": "ul."
  },
  {
    "idulica": "11139",
    "nazwa": "Lipowa",
    "rodzaj": "ul."
  },
  {
    "idulica": "36912",
    "nazwa": "ks. Jerzego Majewskiego",
    "rodzaj": "ul."
  },
  {
    "idulica": "36913",
    "nazwa": "Stanisława Supłatowicza",
    "rodzaj": "ul."
  }
]