[
  {
    "idulica": "03098",
    "nazwa": "Cisowa",
    "rodzaj": "ul."
  },
  {
    "idulica": "14029",
    "nazwa": "Nasławicka",
    "rodzaj": "ul."
  },
  {
    "idulica": "14330",
    "nazwa": "Nowa",
    "rodzaj": "ul."
  },
  {
    "idulica": "15710",
    "nazwa": "Parkowa",
    "rodzaj": "ul."
  },
  {
    "idulica": "17171",
    "nazwa": "Poprzeczna",
    "rodzaj": "ul."
  },
  {
    "idulica": "17191",
    "nazwa": "Poranna",
    "rodzaj": "ul."
  },
  {
    "idulica": "22323",
    "nazwa": "Ślężańska",
    "rodzaj": "ul."
  },
  {
    "idulica": "21101",
    "nazwa": "Stawowa",
    "rodzaj": "ul."
  },
  {
    "idulica": "26367",
    "nazwa": "Żabia",
    "rodzaj": "ul."
  }
]