[
  {
    "idulica": "42986",
    "nazwa": "Cerkwicka",
    "rodzaj": "ul."
  },
  {
    "idulica": "05635",
    "nazwa": "Główna",
    "rodzaj": "ul."
  },
  {
    "idulica": "09546",
    "nazwa": "Kościelna",
    "rodzaj": "ul."
  },
  {
    "idulica": "10898",
    "nazwa": "Leśna",
    "rodzaj": "ul."
  },
  {
    "idulica": "42985",
    "nazwa": "Na Poletka",
    "rodzaj": "ul."
  },
  {
    "idulica": "15710",
    "nazwa": "Parkowa",
    "rodzaj": "ul."
  },
  {
    "idulica": "42984",
    "nazwa": "Przymuszewska",
    "rodzaj": "ul."
  },
  {
    "idulica": "46676",
    "nazwa": "Skwer św. Jana Pawła II",
    "rodzaj": "skwer"
  },
  {
    "idulica": "20641",
    "nazwa": "Spacerowa",
    "rodzaj": "ul."
  },
  {
    "idulica": "20677",
    "nazwa": "Spokojna",
    "rodzaj": "ul."
  },
  {
    "idulica": "21970",
    "nazwa": "Szkolna",
    "rodzaj": "ul."
  }
]