[
  {
    "idulica": "01742",
    "nazwa": "Bolesława Chrobrego",
    "rodzaj": "ul."
  },
  {
    "idulica": "02533",
    "nazwa": "Bzowska",
    "rodzaj": "ul."
  },
  {
    "idulica": "29905",
    "nazwa": "Centuria",
    "rodzaj": "ul."
  },
  {
    "idulica": "02974",
    "nazwa": "Cicha",
    "rodzaj": "ul."
  },
  {
    "idulica": "03114",
    "nazwa": "Cmentarna",
    "rodzaj": "ul."
  },
  {
    "idulica": "06637",
    "nazwa": "Hetmańska",
    "rodzaj": "ul."
  },
  {
    "idulica": "10003",
    "nazwa": "Królowej Jadwigi",
    "rodzaj": "ul."
  },
  {
    "idulica": "20431",
    "nazwa": "Jana III Sobieskiego",
    "rodzaj": "ul."
  },
  {
    "idulica": "07635",
    "nazwa": "Józefów",
    "rodzaj": "ul."
  },
  {
    "idulica": "08979",
    "nazwa": "Kolorowa",
    "rodzaj": "ul."
  },
  {
    "idulica": "09182",
    "nazwa": "Konopnickiej",
    "rodzaj": "ul."
  },
  {
    "idulica": "09276",
    "nazwa": "Kopernika",
    "rodzaj": "ul."
  },
  {
    "idulica": "09572",
    "nazwa": "Kościuszki",
    "rodzaj": "ul."
  },
  {
    "idulica": "09826",
    "nazwa": "Krasickiego",
    "rodzaj": "ul."
  },
  {
    "idulica": "10009",
    "nazwa": "Krótka",
    "rodzaj": "ul."
  },
  {
    "idulica": "10223",
    "nazwa": "Książęca",
    "rodzaj": "ul."
  },
  {
    "idulica": "10601",
    "nazwa": "Lachowizna",
    "rodzaj": "ul."
  },
  {
    "idulica": "10898",
    "nazwa": "Leśna",
    "rodzaj": "ul."
  },
  {
    "idulica": "11926",
    "nazwa": "1 Maja",
    "rodzaj": "ul."
  },
  {
    "idulica": "12065",
    "nazwa": "Malinowa",
    "rodzaj": "ul."
  },
  {
    "idulica": "12734",
    "nazwa": "Mickiewicza",
    "rodzaj": "ul."
  },
  {
    "idulica": "12832",
    "nazwa": "Mieszka I",
    "rodzaj": "ul."
  },
  {
    "idulica": "13379",
    "nazwa": "Mostowa",
    "rodzaj": "ul."
  },
  {
    "idulica": "14015",
    "nazwa": "Narutowicza",
    "rodzaj": "ul."
  },
  {
    "idulica": "14535",
    "nazwa": "Nowy Świat",
    "rodzaj": "ul."
  },
  {
    "idulica": "14834",
    "nazwa": "Ogrodowa",
    "rodzaj": "ul."
  },
  {
    "idulica": "14995",
    "nazwa": "Olkuska",
    "rodzaj": "ul."
  },
  {
    "idulica": "15211",
    "nazwa": "Elizy Orzeszkowej",
    "rodzaj": "ul."
  },
  {
    "idulica": "15524",
    "nazwa": "Paderewskiego",
    "rodzaj": "ul."
  },
  {
    "idulica": "16046",
    "nazwa": "Piastowska",
    "rodzaj": "ul."
  },
  {
    "idulica": "51287",
    "nazwa": "Plac Piłsudskiego",
    "rodzaj": "pl."
  },
  {
    "idulica": "16414",
    "nazwa": "Plac Wolności",
    "rodzaj": "pl."
  },
  {
    "idulica": "17011",
    "nazwa": "Polna",
    "rodzaj": "ul."
  },
  {
    "idulica": "17070",
    "nazwa": "Południowa",
    "rodzaj": "ul."
  },
  {
    "idulica": "19000",
    "nazwa": "Różana",
    "rodzaj": "ul."
  },
  {
    "idulica": "19562",
    "nazwa": "Sawickiej",
    "rodzaj": "ul."
  },
  {
    "idulica": "19830",
    "nazwa": "Sienkiewicza",
    "rodzaj": "ul."
  },
  {
    "idulica": "37683",
    "nazwa": "Generała Sikorskiego",
    "rodzaj": "ul."
  },
  {
    "idulica": "20254",
    "nazwa": "Słoneczna",
    "rodzaj": "ul."
  },
  {
    "idulica": "20286",
    "nazwa": "Słowackiego",
    "rodzaj": "ul."
  },
  {
    "idulica": "20641",
    "nazwa": "Spacerowa",
    "rodzaj": "ul."
  },
  {
    "idulica": "20677",
    "nazwa": "Spokojna",
    "rodzaj": "ul."
  },
  {
    "idulica": "00891",
    "nazwa": "Stefana Batorego",
    "rodzaj": "ul."
  },
  {
    "idulica": "21925",
    "nazwa": "Szeroka",
    "rodzaj": "ul."
  },
  {
    "idulica": "21970",
    "nazwa": "Szkolna",
    "rodzaj": "ul."
  },
  {
    "idulica": "24494",
    "nazwa": "Władysława Jagiełły",
    "rodzaj": "ul."
  },
  {
    "idulica": "24550",
    "nazwa": "Wodna",
    "rodzaj": "ul."
  },
  {
    "idulica": "24870",
    "nazwa": "Wrzosowa",
    "rodzaj": "ul."
  },
  {
    "idulica": "24879",
    "nazwa": "Wschodnia",
    "rodzaj": "ul."
  }
]