[
  {
    "idulica": "04034",
    "nazwa": "Dolna",
    "rodzaj": "ul."
  },
  {
    "idulica": "07380",
    "nazwa": "Jaśminowa",
    "rodzaj": "ul."
  },
  {
    "idulica": "07804",
    "nazwa": "Kalinowa",
    "rodzaj": "ul."
  },
  {
    "idulica": "11596",
    "nazwa": "Łąkowa",
    "rodzaj": "ul."
  },
  {
    "idulica": "11067",
    "nazwa": "Liliowa",
    "rodzaj": "ul."
  },
  {
    "idulica": "16900",
    "nazwa": "Pogodna",
    "rodzaj": "ul."
  },
  {
    "idulica": "20641",
    "nazwa": "Spacerowa",
    "rodzaj": "ul."
  },
  {
    "idulica": "20677",
    "nazwa": "Spokojna",
    "rodzaj": "ul."
  },
  {
    "idulica": "24885",
    "nazwa": "Wspólna",
    "rodzaj": "ul."
  },
  {
    "idulica": "25316",
    "nazwa": "Zaciszna",
    "rodzaj": "ul."
  }
]