[
  {
    "idmiejscowosc": "0748224",
    "nazwa": "Bąsewice"
  },
  {
    "idmiejscowosc": "0748230",
    "nazwa": "Chocielewko"
  },
  {
    "idmiejscowosc": "0748260",
    "nazwa": "Czarnówko"
  },
  {
    "idmiejscowosc": "0748276",
    "nazwa": "Darżewo"
  },
  {
    "idmiejscowosc": "0748543",
    "nazwa": "Darżkowo"
  },
  {
    "idmiejscowosc": "0748299",
    "nazwa": "Dziechlino"
  },
  {
    "idmiejscowosc": "0748307",
    "nazwa": "Garczegorze"
  },
  {
    "idmiejscowosc": "0748448",
    "nazwa": "Jamy"
  },
  {
    "idmiejscowosc": "0748313",
    "nazwa": "Janisławiec"
  },
  {
    "idmiejscowosc": "0748320",
    "nazwa": "Janowice"
  },
  {
    "idmiejscowosc": "0748336",
    "nazwa": "Janowiczki"
  },
  {
    "idmiejscowosc": "0748342",
    "nazwa": "Kanin"
  },
  {
    "idmiejscowosc": "0748359",
    "nazwa": "Karlikowo Lęborskie"
  },
  {
    "idmiejscowosc": "0748365",
    "nazwa": "Kębłowo Nowowiejskie"
  },
  {
    "idmiejscowosc": "0748388",
    "nazwa": "Krępa Kaszubska"
  },
  {
    "idmiejscowosc": "0748282",
    "nazwa": "Laska"
  },
  {
    "idmiejscowosc": "0748394",
    "nazwa": "Leśnice"
  },
  {
    "idmiejscowosc": "0748419",
    "nazwa": "Lędziechowo"
  },
  {
    "idmiejscowosc": "0748425",
    "nazwa": "Lubowidz"
  },
  {
    "idmiejscowosc": "0748460",
    "nazwa": "Łebień"
  },
  {
    "idmiejscowosc": "0748371",
    "nazwa": "Łowcze"
  },
  {
    "idmiejscowosc": "0748454",
    "nazwa": "Ługi"
  },
  {
    "idmiejscowosc": "0748477",
    "nazwa": "Małoszyce"
  },
  {
    "idmiejscowosc": "0748490",
    "nazwa": "Mosty"
  },
  {
    "idmiejscowosc": "0748508",
    "nazwa": "Niebędzino"
  },
  {
    "idmiejscowosc": "0997230",
    "nazwa": "Nisko"
  },
  {
    "idmiejscowosc": "0748514",
    "nazwa": "Nowa Wieś Lęborska"
  },
  {
    "idmiejscowosc": "0748520",
    "nazwa": "Obliwice"
  },
  {
    "idmiejscowosc": "0748402",
    "nazwa": "Piaskowa"
  },
  {
    "idmiejscowosc": "0748537",
    "nazwa": "Pogorszewo"
  },
  {
    "idmiejscowosc": "0748550",
    "nazwa": "Pogorzelice"
  },
  {
    "idmiejscowosc": "0748566",
    "nazwa": "Redkowice"
  },
  {
    "idmiejscowosc": "0748572",
    "nazwa": "Rekowo Lęborskie"
  },
  {
    "idmiejscowosc": "0748589",
    "nazwa": "Rozgorze"
  },
  {
    "idmiejscowosc": "0748483",
    "nazwa": "Rybki"
  },
  {
    "idmiejscowosc": "0748431",
    "nazwa": "Rybnik"
  },
  {
    "idmiejscowosc": "0997246",
    "nazwa": "Szydlice"
  },
  {
    "idmiejscowosc": "0748595",
    "nazwa": "Tawęcino"
  },
  {
    "idmiejscowosc": "0748603",
    "nazwa": "Wilkowo Nowowiejskie"
  },
  {
    "idmiejscowosc": "0748610",
    "nazwa": "Żelazkowo"
  }
]