[
  {
    "idulica": "04686",
    "nazwa": "Dzika",
    "rodzaj": "ul."
  },
  {
    "idulica": "10562",
    "nazwa": "Kwiatowa",
    "rodzaj": "ul."
  },
  {
    "idulica": "11596",
    "nazwa": "Łąkowa",
    "rodzaj": "ul."
  },
  {
    "idulica": "20641",
    "nazwa": "Spacerowa",
    "rodzaj": "ul."
  },
  {
    "idulica": "21325",
    "nazwa": "Strumykowa",
    "rodzaj": "ul."
  },
  {
    "idulica": "24798",
    "nazwa": "Wólczyńska",
    "rodzaj": "ul."
  },
  {
    "idulica": "25274",
    "nazwa": "Zaborowska",
    "rodzaj": "ul."
  },
  {
    "idulica": "25944",
    "nazwa": "Zdrojowa",
    "rodzaj": "ul."
  }
]