[
  {
    "idulica": "03296",
    "nazwa": "Czarnoleska",
    "rodzaj": "ul."
  },
  {
    "idulica": "04572",
    "nazwa": "Działkowa",
    "rodzaj": "ul."
  },
  {
    "idulica": "07059",
    "nazwa": "Jagodowa",
    "rodzaj": "ul."
  },
  {
    "idulica": "14334",
    "nazwa": "Nowa Łąka",
    "rodzaj": "ul."
  },
  {
    "idulica": "18322",
    "nazwa": "Radosna",
    "rodzaj": "ul."
  },
  {
    "idulica": "20998",
    "nazwa": "Starowiejska",
    "rodzaj": "ul."
  },
  {
    "idulica": "26359",
    "nazwa": "Źródlana",
    "rodzaj": "ul."
  }
]