[
  {
    "idulica": "01866",
    "nazwa": "Borowska",
    "rodzaj": "ul."
  },
  {
    "idulica": "02276",
    "nazwa": "Brzozowa",
    "rodzaj": "ul."
  },
  {
    "idulica": "02387",
    "nazwa": "Bukowa",
    "rodzaj": "ul."
  },
  {
    "idulica": "02396",
    "nazwa": "Bukowska",
    "rodzaj": "ul."
  },
  {
    "idulica": "02974",
    "nazwa": "Cicha",
    "rodzaj": "ul."
  },
  {
    "idulica": "03186",
    "nazwa": "Cynkowa",
    "rodzaj": "ul."
  },
  {
    "idulica": "03839",
    "nazwa": "Długa",
    "rodzaj": "ul."
  },
  {
    "idulica": "04434",
    "nazwa": "Dworcowa",
    "rodzaj": "ul."
  },
  {
    "idulica": "05962",
    "nazwa": "Górnicza",
    "rodzaj": "ul."
  },
  {
    "idulica": "05852",
    "nazwa": "Gospodarcza",
    "rodzaj": "ul."
  },
  {
    "idulica": "06029",
    "nazwa": "Grabowa",
    "rodzaj": "ul."
  },
  {
    "idulica": "06075",
    "nazwa": "Graniczna",
    "rodzaj": "ul."
  },
  {
    "idulica": "06412",
    "nazwa": "Gwarków",
    "rodzaj": "ul."
  },
  {
    "idulica": "06825",
    "nazwa": "Hutnicza",
    "rodzaj": "ul."
  },
  {
    "idulica": "07582",
    "nazwa": "Jodłowa",
    "rodzaj": "ul."
  },
  {
    "idulica": "08828",
    "nazwa": "Kolejowa",
    "rodzaj": "ul."
  },
  {
    "idulica": "09582",
    "nazwa": "Tadeusza Kościuszki",
    "rodzaj": "ul."
  },
  {
    "idulica": "09830",
    "nazwa": "Ignacego Krasickiego",
    "rodzaj": "ul."
  },
  {
    "idulica": "10009",
    "nazwa": "Krótka",
    "rodzaj": "ul."
  },
  {
    "idulica": "10898",
    "nazwa": "Leśna",
    "rodzaj": "ul."
  },
  {
    "idulica": "11139",
    "nazwa": "Lipowa",
    "rodzaj": "ul."
  },
  {
    "idulica": "11926",
    "nazwa": "1 Maja",
    "rodzaj": "ul."
  },
  {
    "idulica": "12674",
    "nazwa": "Karola Miarki",
    "rodzaj": "ul."
  },
  {
    "idulica": "12740",
    "nazwa": "Adama Mickiewicza",
    "rodzaj": "ul."
  },
  {
    "idulica": "12848",
    "nazwa": "Międzygórze",
    "rodzaj": "ul."
  },
  {
    "idulica": "13132",
    "nazwa": "Młyńska",
    "rodzaj": "ul."
  },
  {
    "idulica": "13379",
    "nazwa": "Mostowa",
    "rodzaj": "ul."
  },
  {
    "idulica": "14203",
    "nazwa": "Niepodległości",
    "rodzaj": "ul."
  },
  {
    "idulica": "14330",
    "nazwa": "Nowa",
    "rodzaj": "ul."
  },
  {
    "idulica": "14834",
    "nazwa": "Ogrodowa",
    "rodzaj": "ul."
  },
  {
    "idulica": "14945",
    "nazwa": "Olchowa",
    "rodzaj": "ul."
  },
  {
    "idulica": "14995",
    "nazwa": "Olkuska",
    "rodzaj": "ul."
  },
  {
    "idulica": "15710",
    "nazwa": "Parkowa",
    "rodzaj": "ul."
  },
  {
    "idulica": "16579",
    "nazwa": "Pocztowa",
    "rodzaj": "ul."
  },
  {
    "idulica": "35444",
    "nazwa": "Polis",
    "rodzaj": "ul."
  },
  {
    "idulica": "17171",
    "nazwa": "Poprzeczna",
    "rodzaj": "ul."
  },
  {
    "idulica": "17366",
    "nazwa": "Powstańców Śląskich",
    "rodzaj": "ul."
  },
  {
    "idulica": "17742",
    "nazwa": "Przemysłowa",
    "rodzaj": "ul."
  },
  {
    "idulica": "17744",
    "nazwa": "Przeń",
    "rodzaj": "ul."
  },
  {
    "idulica": "17963",
    "nazwa": "Przymiarki",
    "rodzaj": "ul."
  },
  {
    "idulica": "27770",
    "nazwa": "Eugeniusza Puza",
    "rodzaj": "ul."
  },
  {
    "idulica": "18652",
    "nazwa": "Władysława Stanisława Reymonta",
    "rodzaj": "ul."
  },
  {
    "idulica": "19834",
    "nazwa": "Henryka Sienkiewicza",
    "rodzaj": "ul."
  },
  {
    "idulica": "19887",
    "nazwa": "Sierszecka",
    "rodzaj": "ul."
  },
  {
    "idulica": "20060",
    "nazwa": "Składowa",
    "rodzaj": "ul."
  },
  {
    "idulica": "20185",
    "nazwa": "Skwer",
    "rodzaj": "ul."
  },
  {
    "idulica": "20210",
    "nazwa": "Sławkowska",
    "rodzaj": "ul."
  },
  {
    "idulica": "20254",
    "nazwa": "Słoneczna",
    "rodzaj": "ul."
  },
  {
    "idulica": "20291",
    "nazwa": "Juliusza Słowackiego",
    "rodzaj": "ul."
  },
  {
    "idulica": "20598",
    "nazwa": "Sosnowa",
    "rodzaj": "ul."
  },
  {
    "idulica": "20641",
    "nazwa": "Spacerowa",
    "rodzaj": "ul."
  },
  {
    "idulica": "20887",
    "nazwa": "Starczynowska",
    "rodzaj": "ul."
  },
  {
    "idulica": "21970",
    "nazwa": "Szkolna",
    "rodzaj": "ul."
  },
  {
    "idulica": "22209",
    "nazwa": "Szybowa",
    "rodzaj": "ul."
  },
  {
    "idulica": "22811",
    "nazwa": "Tłukienka",
    "rodzaj": "ul."
  },
  {
    "idulica": "22880",
    "nazwa": "Topolowa",
    "rodzaj": "ul."
  },
  {
    "idulica": "23422",
    "nazwa": "Urzędowa",
    "rodzaj": "ul."
  },
  {
    "idulica": "23624",
    "nazwa": "Wapienna",
    "rodzaj": "ul."
  },
  {
    "idulica": "24048",
    "nazwa": "Wiejska",
    "rodzaj": "ul."
  },
  {
    "idulica": "24412",
    "nazwa": "Wiśniowa",
    "rodzaj": "ul."
  },
  {
    "idulica": "24546",
    "nazwa": "Wodąca",
    "rodzaj": "ul."
  },
  {
    "idulica": "24550",
    "nazwa": "Wodna",
    "rodzaj": "ul."
  },
  {
    "idulica": "24628",
    "nazwa": "Wojska Polskiego",
    "rodzaj": "ul."
  },
  {
    "idulica": "48637",
    "nazwa": "Włodzimierza Woźniczki",
    "rodzaj": "ul."
  },
  {
    "idulica": "24977",
    "nazwa": "Wygiełza",
    "rodzaj": "ul."
  },
  {
    "idulica": "25133",
    "nazwa": "Wyzwolenia",
    "rodzaj": "ul."
  },
  {
    "idulica": "30215",
    "nazwa": "ks. Bolesława Zelka",
    "rodzaj": "ul."
  },
  {
    "idulica": "26081",
    "nazwa": "Zielona",
    "rodzaj": "ul."
  },
  {
    "idulica": "26326",
    "nazwa": "Zwycięstwa",
    "rodzaj": "ul."
  }
]