[
  {
    "idulica": "00518",
    "nazwa": "Azaliowa",
    "rodzaj": "ul."
  },
  {
    "idulica": "01458",
    "nazwa": "Błękitna",
    "rodzaj": "ul."
  },
  {
    "idulica": "02768",
    "nazwa": "Chmielna",
    "rodzaj": "ul."
  },
  {
    "idulica": "02817",
    "nazwa": "Choinkowa",
    "rodzaj": "ul."
  },
  {
    "idulica": "03032",
    "nazwa": "Ciepła",
    "rodzaj": "ul."
  },
  {
    "idulica": "03928",
    "nazwa": "Dobra",
    "rodzaj": "ul."
  },
  {
    "idulica": "07290",
    "nazwa": "Jarzębinowa",
    "rodzaj": "ul."
  },
  {
    "idulica": "07394",
    "nazwa": "Jaworowa",
    "rodzaj": "ul."
  },
  {
    "idulica": "07804",
    "nazwa": "Kalinowa",
    "rodzaj": "ul."
  },
  {
    "idulica": "17011",
    "nazwa": "Polna",
    "rodzaj": "ul."
  },
  {
    "idulica": "18322",
    "nazwa": "Radosna",
    "rodzaj": "ul."
  },
  {
    "idulica": "19709",
    "nazwa": "Serwitutowa",
    "rodzaj": "ul."
  },
  {
    "idulica": "20301",
    "nazwa": "Słowikowa",
    "rodzaj": "ul."
  },
  {
    "idulica": "20641",
    "nazwa": "Spacerowa",
    "rodzaj": "ul."
  },
  {
    "idulica": "20683",
    "nazwa": "Sportowa",
    "rodzaj": "ul."
  },
  {
    "idulica": "23406",
    "nazwa": "Urocza",
    "rodzaj": "ul."
  },
  {
    "idulica": "49862",
    "nazwa": "Uśmiech lasu",
    "rodzaj": "ul."
  },
  {
    "idulica": "23814",
    "nazwa": "Wczasowa",
    "rodzaj": "ul."
  },
  {
    "idulica": "24870",
    "nazwa": "Wrzosowa",
    "rodzaj": "ul."
  },
  {
    "idulica": "24882",
    "nazwa": "Wspaniała",
    "rodzaj": "ul."
  },
  {
    "idulica": "26081",
    "nazwa": "Zielona",
    "rodzaj": "ul."
  },
  {
    "idulica": "26188",
    "nazwa": "Złota",
    "rodzaj": "ul."
  },
  {
    "idulica": "26585",
    "nazwa": "Żurawinowa",
    "rodzaj": "ul."
  }
]