[
  {
    "idmiejscowosc": "1046292",
    "nazwa": "Anielin"
  },
  {
    "idmiejscowosc": "0468950",
    "nazwa": "Aptynty"
  },
  {
    "idmiejscowosc": "0468967",
    "nazwa": "Arklity"
  },
  {
    "idmiejscowosc": "0468980",
    "nazwa": "Asuny"
  },
  {
    "idmiejscowosc": "0468996",
    "nazwa": "Barciany"
  },
  {
    "idmiejscowosc": "0469027",
    "nazwa": "Błędowo"
  },
  {
    "idmiejscowosc": "0469033",
    "nazwa": "Bobrowo"
  },
  {
    "idmiejscowosc": "1046300",
    "nazwa": "Bogusławki"
  },
  {
    "idmiejscowosc": "0469458",
    "nazwa": "Borszyny"
  },
  {
    "idmiejscowosc": "0469205",
    "nazwa": "Cacki"
  },
  {
    "idmiejscowosc": "0469040",
    "nazwa": "Czaczek"
  },
  {
    "idmiejscowosc": "0469056",
    "nazwa": "Dębiany"
  },
  {
    "idmiejscowosc": "0469122",
    "nazwa": "Dobrzykowo"
  },
  {
    "idmiejscowosc": "0469062",
    "nazwa": "Drogosze"
  },
  {
    "idmiejscowosc": "0469085",
    "nazwa": "Duje"
  },
  {
    "idmiejscowosc": "0469091",
    "nazwa": "Frączkowo"
  },
  {
    "idmiejscowosc": "0469688",
    "nazwa": "Garbnik"
  },
  {
    "idmiejscowosc": "0469116",
    "nazwa": "Garbno"
  },
  {
    "idmiejscowosc": "0469145",
    "nazwa": "Gęsie Góry"
  },
  {
    "idmiejscowosc": "0469168",
    "nazwa": "Gęsiki"
  },
  {
    "idmiejscowosc": "0469174",
    "nazwa": "Gęsiniec Wielki"
  },
  {
    "idmiejscowosc": "0469659",
    "nazwa": "Glinka"
  },
  {
    "idmiejscowosc": "0469197",
    "nazwa": "Główczyno"
  },
  {
    "idmiejscowosc": "0469180",
    "nazwa": "Gościeradowo"
  },
  {
    "idmiejscowosc": "0468973",
    "nazwa": "Górki"
  },
  {
    "idmiejscowosc": "0469501",
    "nazwa": "Gradowo"
  },
  {
    "idmiejscowosc": "0469211",
    "nazwa": "Gumniska"
  },
  {
    "idmiejscowosc": "0469228",
    "nazwa": "Kąpławki"
  },
  {
    "idmiejscowosc": "0469234",
    "nazwa": "Kiemławki Małe"
  },
  {
    "idmiejscowosc": "0469240",
    "nazwa": "Kiemławki Wielkie"
  },
  {
    "idmiejscowosc": "0469257",
    "nazwa": "Kolwiny"
  },
  {
    "idmiejscowosc": "0469100",
    "nazwa": "Koskajmy"
  },
  {
    "idmiejscowosc": "0469263",
    "nazwa": "Kotki"
  },
  {
    "idmiejscowosc": "0469270",
    "nazwa": "Krelikiejmy"
  },
  {
    "idmiejscowosc": "0469286",
    "nazwa": "Krymławki"
  },
  {
    "idmiejscowosc": "0469292",
    "nazwa": "Krzeczewo"
  },
  {
    "idmiejscowosc": "0469151",
    "nazwa": "Kudwiny"
  },
  {
    "idmiejscowosc": "1046317",
    "nazwa": "Kurkławki"
  },
  {
    "idmiejscowosc": "0469300",
    "nazwa": "Maciejki"
  },
  {
    "idmiejscowosc": "0469317",
    "nazwa": "Markławka"
  },
  {
    "idmiejscowosc": "0469330",
    "nazwa": "Markuzy"
  },
  {
    "idmiejscowosc": "0469346",
    "nazwa": "Michałkowo"
  },
  {
    "idmiejscowosc": "0469352",
    "nazwa": "Modgarby"
  },
  {
    "idmiejscowosc": "0469369",
    "nazwa": "Mołtajny"
  },
  {
    "idmiejscowosc": "0469375",
    "nazwa": "Momajny"
  },
  {
    "idmiejscowosc": "0469607",
    "nazwa": "Moruny"
  },
  {
    "idmiejscowosc": "0469412",
    "nazwa": "Niedziałki"
  },
  {
    "idmiejscowosc": "0469406",
    "nazwa": "Niedziały"
  },
  {
    "idmiejscowosc": "1046323",
    "nazwa": "Nowe Borszyny"
  },
  {
    "idmiejscowosc": "0469381",
    "nazwa": "Nowy Dwór Momajński"
  },
  {
    "idmiejscowosc": "0469429",
    "nazwa": "Ogródki"
  },
  {
    "idmiejscowosc": "1046330",
    "nazwa": "Oleszka"
  },
  {
    "idmiejscowosc": "0469435",
    "nazwa": "Pastwiska"
  },
  {
    "idmiejscowosc": "0469702",
    "nazwa": "Pieszewo"
  },
  {
    "idmiejscowosc": "0469398",
    "nazwa": "Piskorze"
  },
  {
    "idmiejscowosc": "1046346",
    "nazwa": "Plinkajmy"
  },
  {
    "idmiejscowosc": "0469323",
    "nazwa": "Płatławki"
  },
  {
    "idmiejscowosc": "0469441",
    "nazwa": "Podławki"
  },
  {
    "idmiejscowosc": "0469004",
    "nazwa": "Radoski Dwór"
  },
  {
    "idmiejscowosc": "0469464",
    "nazwa": "Radosze"
  },
  {
    "idmiejscowosc": "0469487",
    "nazwa": "Rodele"
  },
  {
    "idmiejscowosc": "0469613",
    "nazwa": "Rowy"
  },
  {
    "idmiejscowosc": "0469493",
    "nazwa": "Ruta"
  },
  {
    "idmiejscowosc": "0469518",
    "nazwa": "Rutka"
  },
  {
    "idmiejscowosc": "0469079",
    "nazwa": "Rzymek"
  },
  {
    "idmiejscowosc": "0469524",
    "nazwa": "Silginy"
  },
  {
    "idmiejscowosc": "1046352",
    "nazwa": "Siwoszewo"
  },
  {
    "idmiejscowosc": "0469547",
    "nazwa": "Skandawa"
  },
  {
    "idmiejscowosc": "0469530",
    "nazwa": "Skandawa"
  },
  {
    "idmiejscowosc": "0469553",
    "nazwa": "Skierki"
  },
  {
    "idmiejscowosc": "0469560",
    "nazwa": "Skoczewo"
  },
  {
    "idmiejscowosc": "0469636",
    "nazwa": "Sławosze"
  },
  {
    "idmiejscowosc": "0469139",
    "nazwa": "Solkieniki"
  },
  {
    "idmiejscowosc": "0469576",
    "nazwa": "Staniszewo"
  },
  {
    "idmiejscowosc": "0469010",
    "nazwa": "Stary Dwór Barciański"
  },
  {
    "idmiejscowosc": "0469582",
    "nazwa": "Suchawa"
  },
  {
    "idmiejscowosc": "0469599",
    "nazwa": "Szaty Wielkie"
  },
  {
    "idmiejscowosc": "0469620",
    "nazwa": "Święty Kamień"
  },
  {
    "idmiejscowosc": "0469642",
    "nazwa": "Taborzec"
  },
  {
    "idmiejscowosc": "1046369",
    "nazwa": "Taborzecki Dwór"
  },
  {
    "idmiejscowosc": "1046398",
    "nazwa": "Wargity"
  },
  {
    "idmiejscowosc": "0469665",
    "nazwa": "Wielewo"
  },
  {
    "idmiejscowosc": "0469671",
    "nazwa": "Wilkowo Małe"
  },
  {
    "idmiejscowosc": "0469694",
    "nazwa": "Winda"
  },
  {
    "idmiejscowosc": "1046412",
    "nazwa": "Wypęk"
  },
  {
    "idmiejscowosc": "1046441",
    "nazwa": "Zalesie"
  },
  {
    "idmiejscowosc": "0469470",
    "nazwa": "Zalewska Góra"
  },
  {
    "idmiejscowosc": "1046458",
    "nazwa": "Zielone"
  }
]