[
  {
    "idulica": "00518",
    "nazwa": "Azaliowa",
    "rodzaj": "ul."
  },
  {
    "idulica": "02657",
    "nazwa": "Chabrowa",
    "rodzaj": "ul."
  },
  {
    "idulica": "03182",
    "nazwa": "Cynamonowa",
    "rodzaj": "ul."
  },
  {
    "idulica": "05027",
    "nazwa": "Fiołkowa",
    "rodzaj": "ul."
  },
  {
    "idulica": "05184",
    "nazwa": "Frezjowa",
    "rodzaj": "ul."
  },
  {
    "idulica": "06608",
    "nazwa": "Herbaciana",
    "rodzaj": "ul."
  },
  {
    "idulica": "06933",
    "nazwa": "Irysowa",
    "rodzaj": "ul."
  },
  {
    "idulica": "07380",
    "nazwa": "Jaśminowa",
    "rodzaj": "ul."
  },
  {
    "idulica": "08772",
    "nazwa": "Kokosowa",
    "rodzaj": "ul."
  },
  {
    "idulica": "09223",
    "nazwa": "Konwaliowa",
    "rodzaj": "ul."
  },
  {
    "idulica": "10718",
    "nazwa": "Lawendowa",
    "rodzaj": "ul."
  },
  {
    "idulica": "11067",
    "nazwa": "Liliowa",
    "rodzaj": "ul."
  },
  {
    "idulica": "11908",
    "nazwa": "Magnoliowa",
    "rodzaj": "ul."
  },
  {
    "idulica": "12004",
    "nazwa": "Makowa",
    "rodzaj": "ul."
  },
  {
    "idulica": "12870",
    "nazwa": "Miętowa",
    "rodzaj": "ul."
  },
  {
    "idulica": "13930",
    "nazwa": "Nagietkowa",
    "rodzaj": "ul."
  },
  {
    "idulica": "16634",
    "nazwa": "Pod Lasem",
    "rodzaj": "ul."
  },
  {
    "idulica": "19000",
    "nazwa": "Różana",
    "rodzaj": "ul."
  },
  {
    "idulica": "19094",
    "nazwa": "Rumiankowa",
    "rodzaj": "ul."
  },
  {
    "idulica": "19549",
    "nazwa": "Sasankowa",
    "rodzaj": "ul."
  },
  {
    "idulica": "20258",
    "nazwa": "Słonecznikowa",
    "rodzaj": "ul."
  },
  {
    "idulica": "23615",
    "nazwa": "Waniliowa",
    "rodzaj": "ul."
  },
  {
    "idulica": "23682",
    "nazwa": "Warszawska",
    "rodzaj": "ul."
  },
  {
    "idulica": "24870",
    "nazwa": "Wrzosowa",
    "rodzaj": "ul."
  }
]