[
  {
    "idmiejscowosc": "0489857",
    "nazwa": "Biały Grunt"
  },
  {
    "idmiejscowosc": "0490091",
    "nazwa": "Bystrz"
  },
  {
    "idmiejscowosc": "0489946",
    "nazwa": "Chajdyce"
  },
  {
    "idmiejscowosc": "0489863",
    "nazwa": "Chochół"
  },
  {
    "idmiejscowosc": "0489870",
    "nazwa": "Cis"
  },
  {
    "idmiejscowosc": "0489886",
    "nazwa": "Długi Borek"
  },
  {
    "idmiejscowosc": "0489917",
    "nazwa": "Jerominy"
  },
  {
    "idmiejscowosc": "0489923",
    "nazwa": "Jerutki"
  },
  {
    "idmiejscowosc": "0489930",
    "nazwa": "Jeruty"
  },
  {
    "idmiejscowosc": "0490100",
    "nazwa": "Kierwik"
  },
  {
    "idmiejscowosc": "0490027",
    "nazwa": "Kobiel"
  },
  {
    "idmiejscowosc": "0489952",
    "nazwa": "Koczek"
  },
  {
    "idmiejscowosc": "0489969",
    "nazwa": "Kolonia"
  },
  {
    "idmiejscowosc": "0489998",
    "nazwa": "Konrady"
  },
  {
    "idmiejscowosc": "0490033",
    "nazwa": "Łąck Mały"
  },
  {
    "idmiejscowosc": "0489975",
    "nazwa": "Łąck Wielki"
  },
  {
    "idmiejscowosc": "0489900",
    "nazwa": "Myszadło"
  },
  {
    "idmiejscowosc": "0490116",
    "nazwa": "Niedźwiedzi Kąt"
  },
  {
    "idmiejscowosc": "0490004",
    "nazwa": "Nowe Czajki"
  },
  {
    "idmiejscowosc": "0490010",
    "nazwa": "Piasutno"
  },
  {
    "idmiejscowosc": "0490040",
    "nazwa": "Połom"
  },
  {
    "idmiejscowosc": "0490056",
    "nazwa": "Powałczyn"
  },
  {
    "idmiejscowosc": "0489981",
    "nazwa": "Racibórz"
  },
  {
    "idmiejscowosc": "0490062",
    "nazwa": "Spychowo"
  },
  {
    "idmiejscowosc": "0490079",
    "nazwa": "Spychowski Piec"
  },
  {
    "idmiejscowosc": "0490085",
    "nazwa": "Spychówko"
  },
  {
    "idmiejscowosc": "0490139",
    "nazwa": "Stare Czajki"
  },
  {
    "idmiejscowosc": "0490122",
    "nazwa": "Szklarnia"
  },
  {
    "idmiejscowosc": "0490145",
    "nazwa": "Świętajno"
  },
  {
    "idmiejscowosc": "0490151",
    "nazwa": "Zielone"
  }
]