[
  {
    "idmiejscowosc": "0527196",
    "nazwa": "Antoniewo"
  },
  {
    "idmiejscowosc": "0527316",
    "nazwa": "Bończa"
  },
  {
    "idmiejscowosc": "1005790",
    "nazwa": "Brzeg"
  },
  {
    "idmiejscowosc": "0527227",
    "nazwa": "Bzowo"
  },
  {
    "idmiejscowosc": "0527233",
    "nazwa": "Bzowo-Goraj"
  },
  {
    "idmiejscowosc": "1005809",
    "nazwa": "Cegielnia"
  },
  {
    "idmiejscowosc": "1005815",
    "nazwa": "Czarne Olendry"
  },
  {
    "idmiejscowosc": "0527204",
    "nazwa": "Dębe"
  },
  {
    "idmiejscowosc": "1005821",
    "nazwa": "Dulinowo"
  },
  {
    "idmiejscowosc": "0527345",
    "nazwa": "Elżbiecin"
  },
  {
    "idmiejscowosc": "0527210",
    "nazwa": "Goraj"
  },
  {
    "idmiejscowosc": "1005838",
    "nazwa": "Jaglina"
  },
  {
    "idmiejscowosc": "0527240",
    "nazwa": "Jędrzejewo"
  },
  {
    "idmiejscowosc": "0527256",
    "nazwa": "Kamionka"
  },
  {
    "idmiejscowosc": "1005844",
    "nazwa": "Kamionka-Wybudowanie"
  },
  {
    "idmiejscowosc": "1005850",
    "nazwa": "Kierzki"
  },
  {
    "idmiejscowosc": "0527262",
    "nazwa": "Klempicz"
  },
  {
    "idmiejscowosc": "0527279",
    "nazwa": "Krucz"
  },
  {
    "idmiejscowosc": "0527285",
    "nazwa": "Krucz"
  },
  {
    "idmiejscowosc": "1005867",
    "nazwa": "Krutecki Bór"
  },
  {
    "idmiejscowosc": "0527291",
    "nazwa": "Kruteczek"
  },
  {
    "idmiejscowosc": "0527300",
    "nazwa": "Lubasz"
  },
  {
    "idmiejscowosc": "0527339",
    "nazwa": "Miłkowo"
  },
  {
    "idmiejscowosc": "0527351",
    "nazwa": "Miłkówko"
  },
  {
    "idmiejscowosc": "0527368",
    "nazwa": "Nowina"
  },
  {
    "idmiejscowosc": "1005873",
    "nazwa": "Parcelaki"
  },
  {
    "idmiejscowosc": "0527374",
    "nazwa": "Prusinowo"
  },
  {
    "idmiejscowosc": "1005880",
    "nazwa": "Psi Koniec"
  },
  {
    "idmiejscowosc": "1005896",
    "nazwa": "Santolina"
  },
  {
    "idmiejscowosc": "0527322",
    "nazwa": "Sławienko"
  },
  {
    "idmiejscowosc": "0527380",
    "nazwa": "Sławno"
  },
  {
    "idmiejscowosc": "0527397",
    "nazwa": "Sokołowo"
  },
  {
    "idmiejscowosc": "0527411",
    "nazwa": "Stajkowo"
  },
  {
    "idmiejscowosc": "1005904",
    "nazwa": "Wybudowanie Antoniewskie"
  },
  {
    "idmiejscowosc": "1005910",
    "nazwa": "Wybudowanie Kruteckie"
  },
  {
    "idmiejscowosc": "1005933",
    "nazwa": "Żabia Ameryka"
  }
]