[
  {
    "idmiejscowosc": "0018684",
    "nazwa": "Aleksandrówka"
  },
  {
    "idmiejscowosc": "0018550",
    "nazwa": "Bordziłówka"
  },
  {
    "idmiejscowosc": "0018738",
    "nazwa": "Brzozówka"
  },
  {
    "idmiejscowosc": "1023693",
    "nazwa": "Bychanie"
  },
  {
    "idmiejscowosc": "0018626",
    "nazwa": "Chominna"
  },
  {
    "idmiejscowosc": "1023730",
    "nazwa": "Góra"
  },
  {
    "idmiejscowosc": "1023753",
    "nazwa": "Hatockie"
  },
  {
    "idmiejscowosc": "1023760",
    "nazwa": "Języczkowe"
  },
  {
    "idmiejscowosc": "1023776",
    "nazwa": "Kaczy Kąt"
  },
  {
    "idmiejscowosc": "1023782",
    "nazwa": "Kamień"
  },
  {
    "idmiejscowosc": "0018744",
    "nazwa": "Karaczony"
  },
  {
    "idmiejscowosc": "0018750",
    "nazwa": "Kątek"
  },
  {
    "idmiejscowosc": "0018572",
    "nazwa": "Kożanówka"
  },
  {
    "idmiejscowosc": "1023799",
    "nazwa": "Miasto"
  },
  {
    "idmiejscowosc": "1023807",
    "nazwa": "Mogiłki"
  },
  {
    "idmiejscowosc": "0018610",
    "nazwa": "Mokre"
  },
  {
    "idmiejscowosc": "0018655",
    "nazwa": "Musiejówka"
  },
  {
    "idmiejscowosc": "1023820",
    "nazwa": "Naddatki"
  },
  {
    "idmiejscowosc": "0018690",
    "nazwa": "Nadpolubicka"
  },
  {
    "idmiejscowosc": "0018709",
    "nazwa": "Nadrossowska"
  },
  {
    "idmiejscowosc": "0018715",
    "nazwa": "Nadworoniecka"
  },
  {
    "idmiejscowosc": "1023836",
    "nazwa": "Peczyska"
  },
  {
    "idmiejscowosc": "1023842",
    "nazwa": "Piaski"
  },
  {
    "idmiejscowosc": "0018589",
    "nazwa": "Podberwy"
  },
  {
    "idmiejscowosc": "1023859",
    "nazwa": "Podrowiny"
  },
  {
    "idmiejscowosc": "0018595",
    "nazwa": "Przedmoście"
  },
  {
    "idmiejscowosc": "0018678",
    "nazwa": "Romaszki"
  },
  {
    "idmiejscowosc": "0018721",
    "nazwa": "Rossosz"
  },
  {
    "idmiejscowosc": "1023865",
    "nazwa": "Rudka"
  },
  {
    "idmiejscowosc": "1023871",
    "nazwa": "Rynek"
  },
  {
    "idmiejscowosc": "1023888",
    "nazwa": "Skupa"
  },
  {
    "idmiejscowosc": "0018632",
    "nazwa": "Sowinne"
  },
  {
    "idmiejscowosc": "1023894",
    "nazwa": "Stawek"
  },
  {
    "idmiejscowosc": "0018566",
    "nazwa": "Szelest"
  },
  {
    "idmiejscowosc": "1023902",
    "nazwa": "Wygon"
  },
  {
    "idmiejscowosc": "0018767",
    "nazwa": "Zabaszta"
  },
  {
    "idmiejscowosc": "1022529",
    "nazwa": "Zabitnik"
  },
  {
    "idmiejscowosc": "1023919",
    "nazwa": "Zagórek"
  },
  {
    "idmiejscowosc": "1023925",
    "nazwa": "Zagrobla"
  },
  {
    "idmiejscowosc": "1023948",
    "nazwa": "Zagumienie"
  },
  {
    "idmiejscowosc": "1023960",
    "nazwa": "Zajudźcowe"
  },
  {
    "idmiejscowosc": "0018649",
    "nazwa": "Zamoście"
  },
  {
    "idmiejscowosc": "0018603",
    "nazwa": "Zaniewszczyzna"
  },
  {
    "idmiejscowosc": "1023983",
    "nazwa": "Zaochoże"
  },
  {
    "idmiejscowosc": "0018661",
    "nazwa": "Zaolzie"
  }
]