[
  {
    "idmiejscowosc": "0871522",
    "nazwa": "Adaminowo"
  },
  {
    "idmiejscowosc": "0871545",
    "nazwa": "Dąb Mały"
  },
  {
    "idmiejscowosc": "0871568",
    "nazwa": "Dąb Polski"
  },
  {
    "idmiejscowosc": "0871551",
    "nazwa": "Dąb Wielki"
  },
  {
    "idmiejscowosc": "0871574",
    "nazwa": "Dębice"
  },
  {
    "idmiejscowosc": "0871597",
    "nazwa": "Dobiegniewo"
  },
  {
    "idmiejscowosc": "0871628",
    "nazwa": "Dobra Wola"
  },
  {
    "idmiejscowosc": "0871640",
    "nazwa": "Gróbce"
  },
  {
    "idmiejscowosc": "1035839",
    "nazwa": "Gróbczyki Drugie"
  },
  {
    "idmiejscowosc": "1035845",
    "nazwa": "Gróbczyki Pierwsze"
  },
  {
    "idmiejscowosc": "0871730",
    "nazwa": "Humlin"
  },
  {
    "idmiejscowosc": "0871605",
    "nazwa": "Jazy"
  },
  {
    "idmiejscowosc": "0871657",
    "nazwa": "Józefowo"
  },
  {
    "idmiejscowosc": "0871887",
    "nazwa": "Józefowo"
  },
  {
    "idmiejscowosc": "0871580",
    "nazwa": "Kolonia Dębice"
  },
  {
    "idmiejscowosc": "0871686",
    "nazwa": "Kosinowo"
  },
  {
    "idmiejscowosc": "0871723",
    "nazwa": "Koszanowo"
  },
  {
    "idmiejscowosc": "0871746",
    "nazwa": "Kruszyn"
  },
  {
    "idmiejscowosc": "0871752",
    "nazwa": "Kruszynek"
  },
  {
    "idmiejscowosc": "1066509",
    "nazwa": "Krzywe Błoto"
  },
  {
    "idmiejscowosc": "0871769",
    "nazwa": "Ludwinowo"
  },
  {
    "idmiejscowosc": "0871775",
    "nazwa": "Ładne"
  },
  {
    "idmiejscowosc": "0871781",
    "nazwa": "Łagiewniki"
  },
  {
    "idmiejscowosc": "0871539",
    "nazwa": "Łączki"
  },
  {
    "idmiejscowosc": "0871893",
    "nazwa": "Łuba Druga"
  },
  {
    "idmiejscowosc": "0871798",
    "nazwa": "Markowo"
  },
  {
    "idmiejscowosc": "0871812",
    "nazwa": "Modzerowo"
  },
  {
    "idmiejscowosc": "0871829",
    "nazwa": "Mostki"
  },
  {
    "idmiejscowosc": "0871835",
    "nazwa": "Mursk"
  },
  {
    "idmiejscowosc": "0871858",
    "nazwa": "Nowa Wieś"
  },
  {
    "idmiejscowosc": "0872042",
    "nazwa": "Pińczata"
  },
  {
    "idmiejscowosc": "0872007",
    "nazwa": "Płaszczyzna"
  },
  {
    "idmiejscowosc": "0871864",
    "nazwa": "Poddębice"
  },
  {
    "idmiejscowosc": "0871870",
    "nazwa": "Potok"
  },
  {
    "idmiejscowosc": "0871918",
    "nazwa": "Przerytka"
  },
  {
    "idmiejscowosc": "0871901",
    "nazwa": "Przyruda"
  },
  {
    "idmiejscowosc": "0871663",
    "nazwa": "Radyszyn"
  },
  {
    "idmiejscowosc": "0871611",
    "nazwa": "Ruda"
  },
  {
    "idmiejscowosc": "0871924",
    "nazwa": "Skoki Duże"
  },
  {
    "idmiejscowosc": "0871930",
    "nazwa": "Skoki Małe"
  },
  {
    "idmiejscowosc": "0872013",
    "nazwa": "Smolarka"
  },
  {
    "idmiejscowosc": "0871982",
    "nazwa": "Smolarskie"
  },
  {
    "idmiejscowosc": "0871947",
    "nazwa": "Smólnik"
  },
  {
    "idmiejscowosc": "0871953",
    "nazwa": "Smólsk"
  },
  {
    "idmiejscowosc": "0871692",
    "nazwa": "Stasin"
  },
  {
    "idmiejscowosc": "0871806",
    "nazwa": "Sykuła"
  },
  {
    "idmiejscowosc": "0871634",
    "nazwa": "Świętosław"
  },
  {
    "idmiejscowosc": "0871976",
    "nazwa": "Telążna Leśna"
  },
  {
    "idmiejscowosc": "0871960",
    "nazwa": "Telążna Stara"
  },
  {
    "idmiejscowosc": "0871999",
    "nazwa": "Warząchewka Królewska"
  },
  {
    "idmiejscowosc": "0872020",
    "nazwa": "Warząchewka Nowa"
  },
  {
    "idmiejscowosc": "0872036",
    "nazwa": "Warząchewka Polska"
  },
  {
    "idmiejscowosc": "0871670",
    "nazwa": "Widoń"
  },
  {
    "idmiejscowosc": "0872059",
    "nazwa": "Wikaryjskie"
  },
  {
    "idmiejscowosc": "1035934",
    "nazwa": "Wikaryjskie"
  },
  {
    "idmiejscowosc": "0872071",
    "nazwa": "Wistka Królewska"
  },
  {
    "idmiejscowosc": "0871700",
    "nazwa": "Wistka Szlachecka"
  },
  {
    "idmiejscowosc": "0872065",
    "nazwa": "Wójtowskie"
  },
  {
    "idmiejscowosc": "0871717",
    "nazwa": "Zuzałka"
  }
]