[
  {
    "idmiejscowosc": "0691234",
    "nazwa": "Aleksandrówka"
  },
  {
    "idmiejscowosc": "0691263",
    "nazwa": "Błażejki"
  },
  {
    "idmiejscowosc": "0691613",
    "nazwa": "Borek"
  },
  {
    "idmiejscowosc": "0691286",
    "nazwa": "Borki"
  },
  {
    "idmiejscowosc": "0691292",
    "nazwa": "Celej"
  },
  {
    "idmiejscowosc": "0691257",
    "nazwa": "Chrusty"
  },
  {
    "idmiejscowosc": "0691300",
    "nazwa": "Guzówka"
  },
  {
    "idmiejscowosc": "0691725",
    "nazwa": "Huta Łukacz"
  },
  {
    "idmiejscowosc": "0691323",
    "nazwa": "Jagodne"
  },
  {
    "idmiejscowosc": "0691352",
    "nazwa": "Jamielne"
  },
  {
    "idmiejscowosc": "0691783",
    "nazwa": "Jamielnik"
  },
  {
    "idmiejscowosc": "0691369",
    "nazwa": "Jamielnik-Kolonia"
  },
  {
    "idmiejscowosc": "0691381",
    "nazwa": "Januszówka"
  },
  {
    "idmiejscowosc": "0691398",
    "nazwa": "Jedlanka"
  },
  {
    "idmiejscowosc": "0691760",
    "nazwa": "Kadzidła"
  },
  {
    "idmiejscowosc": "0691412",
    "nazwa": "Kamionka"
  },
  {
    "idmiejscowosc": "0691441",
    "nazwa": "Kapice"
  },
  {
    "idmiejscowosc": "0691458",
    "nazwa": "Kienkówka"
  },
  {
    "idmiejscowosc": "0691464",
    "nazwa": "Kisielsk"
  },
  {
    "idmiejscowosc": "0691240",
    "nazwa": "Kolonia"
  },
  {
    "idmiejscowosc": "0691530",
    "nazwa": "Kuropac"
  },
  {
    "idmiejscowosc": "0691470",
    "nazwa": "Łosiniec"
  },
  {
    "idmiejscowosc": "0691553",
    "nazwa": "Mirek"
  },
  {
    "idmiejscowosc": "0691487",
    "nazwa": "Mizary"
  },
  {
    "idmiejscowosc": "0691317",
    "nazwa": "Nowa Guzówka"
  },
  {
    "idmiejscowosc": "0691493",
    "nazwa": "Nowa Prawda"
  },
  {
    "idmiejscowosc": "0691501",
    "nazwa": "Nowe Kobiałki"
  },
  {
    "idmiejscowosc": "0691547",
    "nazwa": "Nowiny"
  },
  {
    "idmiejscowosc": "0691518",
    "nazwa": "Nowy Jamielnik"
  },
  {
    "idmiejscowosc": "0691429",
    "nazwa": "Piaski"
  },
  {
    "idmiejscowosc": "0691671",
    "nazwa": "Pieńki"
  },
  {
    "idmiejscowosc": "0691688",
    "nazwa": "Podlasie"
  },
  {
    "idmiejscowosc": "0691694",
    "nazwa": "Podstawek"
  },
  {
    "idmiejscowosc": "0691375",
    "nazwa": "Pustki"
  },
  {
    "idmiejscowosc": "0691524",
    "nazwa": "Rosy"
  },
  {
    "idmiejscowosc": "0691330",
    "nazwa": "Rozkosz"
  },
  {
    "idmiejscowosc": "0691576",
    "nazwa": "Róża"
  },
  {
    "idmiejscowosc": "0691560",
    "nazwa": "Róża Podgórna"
  },
  {
    "idmiejscowosc": "0691820",
    "nazwa": "Ruda"
  },
  {
    "idmiejscowosc": "0691599",
    "nazwa": "Stara Prawda"
  },
  {
    "idmiejscowosc": "0691607",
    "nazwa": "Stara Róża"
  },
  {
    "idmiejscowosc": "0691636",
    "nazwa": "Stare Kobiałki"
  },
  {
    "idmiejscowosc": "0691642",
    "nazwa": "Stary Jamielnik"
  },
  {
    "idmiejscowosc": "0691659",
    "nazwa": "Szyszki"
  },
  {
    "idmiejscowosc": "0691665",
    "nazwa": "Toczyska"
  },
  {
    "idmiejscowosc": "0691702",
    "nazwa": "Turzec"
  },
  {
    "idmiejscowosc": "0691582",
    "nazwa": "Warkocz"
  },
  {
    "idmiejscowosc": "0691346",
    "nazwa": "Wesołówka"
  },
  {
    "idmiejscowosc": "0691435",
    "nazwa": "Wiśniów"
  },
  {
    "idmiejscowosc": "0691719",
    "nazwa": "Wiśniówka"
  },
  {
    "idmiejscowosc": "0691731",
    "nazwa": "Wola Kisielska"
  },
  {
    "idmiejscowosc": "0691748",
    "nazwa": "Wólka Poznańska"
  },
  {
    "idmiejscowosc": "0691754",
    "nazwa": "Wólka Różańska"
  },
  {
    "idmiejscowosc": "0691270",
    "nazwa": "Za Mostem"
  },
  {
    "idmiejscowosc": "0691790",
    "nazwa": "Zabiele"
  },
  {
    "idmiejscowosc": "0691620",
    "nazwa": "Zamoście"
  },
  {
    "idmiejscowosc": "0691808",
    "nazwa": "Zaskwiera"
  },
  {
    "idmiejscowosc": "0691814",
    "nazwa": "Zgórznica"
  }
]