[
  {
    "idulica": "04034",
    "nazwa": "Dolna",
    "rodzaj": "ul."
  },
  {
    "idulica": "04446",
    "nazwa": "Dworska",
    "rodzaj": "ul."
  },
  {
    "idulica": "07626",
    "nazwa": "św. Józefa",
    "rodzaj": "ul."
  },
  {
    "idulica": "07842",
    "nazwa": "Kalwaryjska",
    "rodzaj": "ul."
  },
  {
    "idulica": "40063",
    "nazwa": "Kowalikowa",
    "rodzaj": "ul."
  },
  {
    "idulica": "14495",
    "nazwa": "Nowowiejska",
    "rodzaj": "ul."
  },
  {
    "idulica": "56090",
    "nazwa": "Ojca Pio",
    "rodzaj": "ul."
  },
  {
    "idulica": "16788",
    "nazwa": "Podlas",
    "rodzaj": "ul."
  },
  {
    "idulica": "17011",
    "nazwa": "Polna",
    "rodzaj": "ul."
  },
  {
    "idulica": "23485",
    "nazwa": "Wadowicka",
    "rodzaj": "ul."
  },
  {
    "idulica": "24885",
    "nazwa": "Wspólna",
    "rodzaj": "ul."
  }
]